{"1": [{"Richmond": {"KI": 155, "MK": 57, "HB": 122, "DI": 277, "GL": 16, "BH": 9, "HO": 41, "TK": 52, "RB": 41, "IF": 48, "CL": 31, "CG": 50, "FF": 18, "FA": 24, "PTS": 105}, "Carlton": {"KI": 189, "MK": 69, "HB": 114, "DI": 303, "GL": 12, "BH": 9, "HO": 26, "TK": 23, "RB": 29, "IF": 54, "CL": 32, "CG": 51, "FF": 24, "FA": 18, "PTS": 81}}, {"Richmond": {"KI": 155, "MK": 57, "HB": 122, "DI": 277, "GL": 16, "BH": 9, "HO": 41, "TK": 52, "RB": 41, "IF": 48, "CL": 31, "CG": 50, "FF": 18, "FA": 24, "PTS": 105}, "Carlton": {"KI": 189, "MK": 69, "HB": 114, "DI": 303, "GL": 12, "BH": 9, "HO": 26, "TK": 23, "RB": 29, "IF": 54, "CL": 32, "CG": 51, "FF": 24, "FA": 18, "PTS": 81}}, {"Richmond": {"KI": 155, "MK": 57, "HB": 122, "DI": 277, "GL": 16, "BH": 9, "HO": 41, "TK": 52, "RB": 41, "IF": 48, "CL": 31, "CG": 50, "FF": 18, "FA": 24, "PTS": 105}, "Carlton": {"KI": 189, "MK": 69, "HB": 114, "DI": 303, "GL": 12, "BH": 9, "HO": 26, "TK": 23, "RB": 29, "IF": 54, "CL": 32, "CG": 51, "FF": 24, "FA": 18, "PTS": 81}}, {"Richmond": {"KI": 155, "MK": 57, "HB": 122, "DI": 277, "GL": 16, "BH": 9, "HO": 41, "TK": 52, "RB": 41, "IF": 48, "CL": 31, "CG": 50, "FF": 18, "FA": 24, "PTS": 105}, "Carlton": {"KI": 189, "MK": 69, "HB": 114, "DI": 303, "GL": 12, "BH": 9, "HO": 26, "TK": 23, "RB": 29, "IF": 54, "CL": 32, "CG": 51, "FF": 24, "FA": 18, "PTS": 81}}, {"Richmond": {"KI": 155, "MK": 57, "HB": 122, "DI": 277, "GL": 16, "BH": 9, "HO": 41, "TK": 52, "RB": 41, "IF": 48, "CL": 31, "CG": 50, "FF": 18, "FA": 24, "PTS": 105}, "Carlton": {"KI": 189, "MK": 69, "HB": 114, "DI": 303, "GL": 12, "BH": 9, "HO": 26, "TK": 23, "RB": 29, "IF": 54, "CL": 32, "CG": 51, "FF": 24, "FA": 18, "PTS": 81}}, {"Richmond": {"KI": 155, "MK": 57, "HB": 122, "DI": 277, "GL": 16, "BH": 9, "HO": 41, "TK": 52, "RB": 41, "IF": 48, "CL": 31, "CG": 50, "FF": 18, "FA": 24, "PTS": 105}, "Carlton": {"KI": 189, "MK": 69, "HB": 114, "DI": 303, "GL": 12, "BH": 9, "HO": 26, "TK": 23, "RB": 29, "IF": 54, "CL": 32, "CG": 51, "FF": 24, "FA": 18, "PTS": 81}}, {"Richmond": {"KI": 155, "MK": 57, "HB": 122, "DI": 277, "GL": 16, "BH": 9, "HO": 41, "TK": 52, "RB": 41, "IF": 48, "CL": 31, "CG": 50, "FF": 18, "FA": 24, "PTS": 105}, "Carlton": {"KI": 189, "MK": 69, "HB": 114, "DI": 303, "GL": 12, "BH": 9, "HO": 26, "TK": 23, "RB": 29, "IF": 54, "CL": 32, "CG": 51, "FF": 24, "FA": 18, "PTS": 81}}, {"Richmond": {"KI": 155, "MK": 57, "HB": 122, "DI": 277, "GL": 16, "BH": 9, "HO": 41, "TK": 52, "RB": 41, "IF": 48, "CL": 31, "CG": 50, "FF": 18, "FA": 24, "PTS": 105}, "Carlton": {"KI": 189, "MK": 69, "HB": 114, "DI": 303, "GL": 12, "BH": 9, "HO": 26, "TK": 23, "RB": 29, "IF": 54, "CL": 32, "CG": 51, "FF": 24, "FA": 18, "PTS": 81}}, {"Richmond": {"KI": 155, "MK": 57, "HB": 122, "DI": 277, "GL": 16, "BH": 9, "HO": 41, "TK": 52, "RB": 41, "IF": 48, "CL": 31, "CG": 50, "FF": 18, "FA": 24, "PTS": 105}, "Carlton": {"KI": 189, "MK": 69, "HB": 114, "DI": 303, "GL": 12, "BH": 9, "HO": 26, "TK": 23, "RB": 29, "IF": 54, "CL": 32, "CG": 51, "FF": 24, "FA": 18, "PTS": 81}}], "2": [{"Richmond": {"KI": 155, "MK": 57, "HB": 122, "DI": 277, "GL": 16, "BH": 9, "HO": 41, "TK": 52, "RB": 41, "IF": 48, "CL": 31, "CG": 50, "FF": 18, "FA": 24, "PTS": 105}, "Carlton": {"KI": 189, "MK": 69, "HB": 114, "DI": 303, "GL": 12, "BH": 9, "HO": 26, "TK": 23, "RB": 29, "IF": 54, "CL": 32, "CG": 51, "FF": 24, "FA": 18, "PTS": 81}}, {"Richmond": {"KI": 155, "MK": 57, "HB": 122, "DI": 277, "GL": 16, "BH": 9, "HO": 41, "TK": 52, "RB": 41, "IF": 48, "CL": 31, "CG": 50, "FF": 18, "FA": 24, "PTS": 105}, "Carlton": {"KI": 189, "MK": 69, "HB": 114, "DI": 303, "GL": 12, "BH": 9, "HO": 26, "TK": 23, "RB": 29, "IF": 54, "CL": 32, "CG": 51, "FF": 24, "FA": 18, "PTS": 81}}, {"Richmond": {"KI": 155, "MK": 57, "HB": 122, "DI": 277, "GL": 16, "BH": 9, "HO": 41, "TK": 52, "RB": 41, "IF": 48, "CL": 31, "CG": 50, "FF": 18, "FA": 24, "PTS": 105}, "Carlton": {"KI": 189, "MK": 69, "HB": 114, "DI": 303, "GL": 12, "BH": 9, "HO": 26, "TK": 23, "RB": 29, "IF": 54, "CL": 32, "CG": 51, "FF": 24, "FA": 18, "PTS": 81}}, {"Richmond": {"KI": 155, "MK": 57, "HB": 122, "DI": 277, "GL": 16, "BH": 9, "HO": 41, "TK": 52, "RB": 41, "IF": 48, "CL": 31, "CG": 50, "FF": 18, "FA": 24, "PTS": 105}, "Carlton": {"KI": 189, "MK": 69, "HB": 114, "DI": 303, "GL": 12, "BH": 9, "HO": 26, "TK": 23, "RB": 29, "IF": 54, "CL": 32, "CG": 51, "FF": 24, "FA": 18, "PTS": 81}}, {"Richmond": {"KI": 155, "MK": 57, "HB": 122, "DI": 277, "GL": 16, "BH": 9, "HO": 41, "TK": 52, "RB": 41, "IF": 48, "CL": 31, "CG": 50, "FF": 18, "FA": 24, "PTS": 105}, "Carlton": {"KI": 189, "MK": 69, "HB": 114, "DI": 303, "GL": 12, "BH": 9, "HO": 26, "TK": 23, "RB": 29, "IF": 54, "CL": 32, "CG": 51, "FF": 24, "FA": 18, "PTS": 81}}, {"Richmond": {"KI": 155, "MK": 57, "HB": 122, "DI": 277, "GL": 16, "BH": 9, "HO": 41, "TK": 52, "RB": 41, "IF": 48, "CL": 31, "CG": 50, "FF": 18, "FA": 24, "PTS": 105}, "Carlton": {"KI": 189, "MK": 69, "HB": 114, "DI": 303, "GL": 12, "BH": 9, "HO": 26, "TK": 23, "RB": 29, "IF": 54, "CL": 32, "CG": 51, "FF": 24, "FA": 18, "PTS": 81}}, {"Richmond": {"KI": 155, "MK": 57, "HB": 122, "DI": 277, "GL": 16, "BH": 9, "HO": 41, "TK": 52, "RB": 41, "IF": 48, "CL": 31, "CG": 50, "FF": 18, "FA": 24, "PTS": 105}, "Carlton": {"KI": 189, "MK": 69, "HB": 114, "DI": 303, "GL": 12, "BH": 9, "HO": 26, "TK": 23, "RB": 29, "IF": 54, "CL": 32, "CG": 51, "FF": 24, "FA": 18, "PTS": 81}}, {"Richmond": {"KI": 155, "MK": 57, "HB": 122, "DI": 277, "GL": 16, "BH": 9, "HO": 41, "TK": 52, "RB": 41, "IF": 48, "CL": 31, "CG": 50, "FF": 18, "FA": 24, "PTS": 105}, "Carlton": {"KI": 189, "MK": 69, "HB": 114, "DI": 303, "GL": 12, "BH": 9, "HO": 26, "TK": 23, "RB": 29, "IF": 54, "CL": 32, "CG": 51, "FF": 24, "FA": 18, "PTS": 81}}, {"Richmond": {"KI": 155, "MK": 57, "HB": 122, "DI": 277, "GL": 16, "BH": 9, "HO": 41, "TK": 52, "RB": 41, "IF": 48, "CL": 31, "CG": 50, "FF": 18, "FA": 24, "PTS": 105}, "Carlton": {"KI": 189, "MK": 69, "HB": 114, "DI": 303, "GL": 12, "BH": 9, "HO": 26, "TK": 23, "RB": 29, "IF": 54, "CL": 32, "CG": 51, "FF": 24, "FA": 18, "PTS": 81}}], "3": [{"Richmond": {"KI": 155, "MK": 57, "HB": 122, "DI": 277, "GL": 16, "BH": 9, "HO": 41, "TK": 52, "RB": 41, "IF": 48, "CL": 31, "CG": 50, "FF": 18, "FA": 24, "PTS": 105}, "Carlton": {"KI": 189, "MK": 69, "HB": 114, "DI": 303, "GL": 12, "BH": 9, "HO": 26, "TK": 23, "RB": 29, "IF": 54, "CL": 32, "CG": 51, "FF": 24, "FA": 18, "PTS": 81}}, {"Richmond": {"KI": 155, "MK": 57, "HB": 122, "DI": 277, "GL": 16, "BH": 9, "HO": 41, "TK": 52, "RB": 41, "IF": 48, "CL": 31, "CG": 50, "FF": 18, "FA": 24, "PTS": 105}, "Carlton": {"KI": 189, "MK": 69, "HB": 114, "DI": 303, "GL": 12, "BH": 9, "HO": 26, "TK": 23, "RB": 29, "IF": 54, "CL": 32, "CG": 51, "FF": 24, "FA": 18, "PTS": 81}}, {"Richmond": {"KI": 155, "MK": 57, "HB": 122, "DI": 277, "GL": 16, "BH": 9, "HO": 41, "TK": 52, "RB": 41, "IF": 48, "CL": 31, "CG": 50, "FF": 18, "FA": 24, "PTS": 105}, "Carlton": {"KI": 189, "MK": 69, "HB": 114, "DI": 303, "GL": 12, "BH": 9, "HO": 26, "TK": 23, "RB": 29, "IF": 54, "CL": 32, "CG": 51, "FF": 24, "FA": 18, "PTS": 81}}, {"Richmond": {"KI": 155, "MK": 57, "HB": 122, "DI": 277, "GL": 16, "BH": 9, "HO": 41, "TK": 52, "RB": 41, "IF": 48, "CL": 31, "CG": 50, "FF": 18, "FA": 24, "PTS": 105}, "Carlton": {"KI": 189, "MK": 69, "HB": 114, "DI": 303, "GL": 12, "BH": 9, "HO": 26, "TK": 23, "RB": 29, "IF": 54, "CL": 32, "CG": 51, "FF": 24, "FA": 18, "PTS": 81}}, {"Richmond": {"KI": 155, "MK": 57, "HB": 122, "DI": 277, "GL": 16, "BH": 9, "HO": 41, "TK": 52, "RB": 41, "IF": 48, "CL": 31, "CG": 50, "FF": 18, "FA": 24, "PTS": 105}, "Carlton": {"KI": 189, "MK": 69, "HB": 114, "DI": 303, "GL": 12, "BH": 9, "HO": 26, "TK": 23, "RB": 29, "IF": 54, "CL": 32, "CG": 51, "FF": 24, "FA": 18, "PTS": 81}}, {"Richmond": {"KI": 155, "MK": 57, "HB": 122, "DI": 277, "GL": 16, "BH": 9, "HO": 41, "TK": 52, "RB": 41, "IF": 48, "CL": 31, "CG": 50, "FF": 18, "FA": 24, "PTS": 105}, "Carlton": {"KI": 189, "MK": 69, "HB": 114, "DI": 303, "GL": 12, "BH": 9, "HO": 26, "TK": 23, "RB": 29, "IF": 54, "CL": 32, "CG": 51, "FF": 24, "FA": 18, "PTS": 81}}, {"Richmond": {"KI": 155, "MK": 57, "HB": 122, "DI": 277, "GL": 16, "BH": 9, "HO": 41, "TK": 52, "RB": 41, "IF": 48, "CL": 31, "CG": 50, "FF": 18, "FA": 24, "PTS": 105}, "Carlton": {"KI": 189, "MK": 69, "HB": 114, "DI": 303, "GL": 12, "BH": 9, "HO": 26, "TK": 23, "RB": 29, "IF": 54, "CL": 32, "CG": 51, "FF": 24, "FA": 18, "PTS": 81}}, {"Richmond": {"KI": 155, "MK": 57, "HB": 122, "DI": 277, "GL": 16, "BH": 9, "HO": 41, "TK": 52, "RB": 41, "IF": 48, "CL": 31, "CG": 50, "FF": 18, "FA": 24, "PTS": 105}, "Carlton": {"KI": 189, "MK": 69, "HB": 114, "DI": 303, "GL": 12, "BH": 9, "HO": 26, "TK": 23, "RB": 29, "IF": 54, "CL": 32, "CG": 51, "FF": 24, "FA": 18, "PTS": 81}}], "4": [{"Richmond": {"KI": 155, "MK": 57, "HB": 122, "DI": 277, "GL": 16, "BH": 9, "HO": 41, "TK": 52, "RB": 41, "IF": 48, "CL": 31, "CG": 50, "FF": 18, "FA": 24, "PTS": 105}, "Carlton": {"KI": 189, "MK": 69, "HB": 114, "DI": 303, "GL": 12, "BH": 9, "HO": 26, "TK": 23, "RB": 29, "IF": 54, "CL": 32, "CG": 51, "FF": 24, "FA": 18, "PTS": 81}}, {"Richmond": {"KI": 155, "MK": 57, "HB": 122, "DI": 277, "GL": 16, "BH": 9, "HO": 41, "TK": 52, "RB": 41, "IF": 48, "CL": 31, "CG": 50, "FF": 18, "FA": 24, "PTS": 105}, "Carlton": {"KI": 189, "MK": 69, "HB": 114, "DI": 303, "GL": 12, "BH": 9, "HO": 26, "TK": 23, "RB": 29, "IF": 54, "CL": 32, "CG": 51, "FF": 24, "FA": 18, "PTS": 81}}, {"Richmond": {"KI": 155, "MK": 57, "HB": 122, "DI": 277, "GL": 16, "BH": 9, "HO": 41, "TK": 52, "RB": 41, "IF": 48, "CL": 31, "CG": 50, "FF": 18, "FA": 24, "PTS": 105}, "Carlton": {"KI": 189, "MK": 69, "HB": 114, "DI": 303, "GL": 12, "BH": 9, "HO": 26, "TK": 23, "RB": 29, "IF": 54, "CL": 32, "CG": 51, "FF": 24, "FA": 18, "PTS": 81}}, {"Richmond": {"KI": 155, "MK": 57, "HB": 122, "DI": 277, "GL": 16, "BH": 9, "HO": 41, "TK": 52, "RB": 41, "IF": 48, "CL": 31, "CG": 50, "FF": 18, "FA": 24, "PTS": 105}, "Carlton": {"KI": 189, "MK": 69, "HB": 114, "DI": 303, "GL": 12, "BH": 9, "HO": 26, "TK": 23, "RB": 29, "IF": 54, "CL": 32, "CG": 51, "FF": 24, "FA": 18, "PTS": 81}}, {"Richmond": {"KI": 155, "MK": 57, "HB": 122, "DI": 277, "GL": 16, "BH": 9, "HO": 41, "TK": 52, "RB": 41, "IF": 48, "CL": 31, "CG": 50, "FF": 18, "FA": 24, "PTS": 105}, "Carlton": {"KI": 189, "MK": 69, "HB": 114, "DI": 303, "GL": 12, "BH": 9, "HO": 26, "TK": 23, "RB": 29, "IF": 54, "CL": 32, "CG": 51, "FF": 24, "FA": 18, "PTS": 81}}, {"Richmond": {"KI": 155, "MK": 57, "HB": 122, "DI": 277, "GL": 16, "BH": 9, "HO": 41, "TK": 52, "RB": 41, "IF": 48, "CL": 31, "CG": 50, "FF": 18, "FA": 24, "PTS": 105}, "Carlton": {"KI": 189, "MK": 69, "HB": 114, "DI": 303, "GL": 12, "BH": 9, "HO": 26, "TK": 23, "RB": 29, "IF": 54, "CL": 32, "CG": 51, "FF": 24, "FA": 18, "PTS": 81}}, {"Richmond": {"KI": 155, "MK": 57, "HB": 122, "DI": 277, "GL": 16, "BH": 9, "HO": 41, "TK": 52, "RB": 41, "IF": 48, "CL": 31, "CG": 50, "FF": 18, "FA": 24, "PTS": 105}, "Carlton": {"KI": 189, "MK": 69, "HB": 114, "DI": 303, "GL": 12, "BH": 9, "HO": 26, "TK": 23, "RB": 29, "IF": 54, "CL": 32, "CG": 51, "FF": 24, "FA": 18, "PTS": 81}}, {"Richmond": {"KI": 155, "MK": 57, "HB": 122, "DI": 277, "GL": 16, "BH": 9, "HO": 41, "TK": 52, "RB": 41, "IF": 48, "CL": 31, "CG": 50, "FF": 18, "FA": 24, "PTS": 105}, "Carlton": {"KI": 189, "MK": 69, "HB": 114, "DI": 303, "GL": 12, "BH": 9, "HO": 26, "TK": 23, "RB": 29, "IF": 54, "CL": 32, "CG": 51, "FF": 24, "FA": 18, "PTS": 81}}, {"Richmond": {"KI": 155, "MK": 57, "HB": 122, "DI": 277, "GL": 16, "BH": 9, "HO": 41, "TK": 52, "RB": 41, "IF": 48, "CL": 31, "CG": 50, "FF": 18, "FA": 24, "PTS": 105}, "Carlton": {"KI": 189, "MK": 69, "HB": 114, "DI": 303, "GL": 12, "BH": 9, "HO": 26, "TK": 23, "RB": 29, "IF": 54, "CL": 32, "CG": 51, "FF": 24, "FA": 18, "PTS": 81}}], "5": [{"Richmond": {"KI": 155, "MK": 57, "HB": 122, "DI": 277, "GL": 16, "BH": 9, "HO": 41, "TK": 52, "RB": 41, "IF": 48, "CL": 31, "CG": 50, "FF": 18, "FA": 24, "PTS": 105}, "Carlton": {"KI": 189, "MK": 69, "HB": 114, "DI": 303, "GL": 12, "BH": 9, "HO": 26, "TK": 23, "RB": 29, "IF": 54, "CL": 32, "CG": 51, "FF": 24, "FA": 18, "PTS": 81}}, {"Richmond": {"KI": 155, "MK": 57, "HB": 122, "DI": 277, "GL": 16, "BH": 9, "HO": 41, "TK": 52, "RB": 41, "IF": 48, "CL": 31, "CG": 50, "FF": 18, "FA": 24, "PTS": 105}, "Carlton": {"KI": 189, "MK": 69, "HB": 114, "DI": 303, "GL": 12, "BH": 9, "HO": 26, "TK": 23, "RB": 29, "IF": 54, "CL": 32, "CG": 51, "FF": 24, "FA": 18, "PTS": 81}}, {"Richmond": {"KI": 155, "MK": 57, "HB": 122, "DI": 277, "GL": 16, "BH": 9, "HO": 41, "TK": 52, "RB": 41, "IF": 48, "CL": 31, "CG": 50, "FF": 18, "FA": 24, "PTS": 105}, "Carlton": {"KI": 189, "MK": 69, "HB": 114, "DI": 303, "GL": 12, "BH": 9, "HO": 26, "TK": 23, "RB": 29, "IF": 54, "CL": 32, "CG": 51, "FF": 24, "FA": 18, "PTS": 81}}, {"Richmond": {"KI": 155, "MK": 57, "HB": 122, "DI": 277, "GL": 16, "BH": 9, "HO": 41, "TK": 52, "RB": 41, "IF": 48, "CL": 31, "CG": 50, "FF": 18, "FA": 24, "PTS": 105}, "Carlton": {"KI": 189, "MK": 69, "HB": 114, "DI": 303, "GL": 12, "BH": 9, "HO": 26, "TK": 23, "RB": 29, "IF": 54, "CL": 32, "CG": 51, "FF": 24, "FA": 18, "PTS": 81}}, {"Richmond": {"KI": 155, "MK": 57, "HB": 122, "DI": 277, "GL": 16, "BH": 9, "HO": 41, "TK": 52, "RB": 41, "IF": 48, "CL": 31, "CG": 50, "FF": 18, "FA": 24, "PTS": 105}, "Carlton": {"KI": 189, "MK": 69, "HB": 114, "DI": 303, "GL": 12, "BH": 9, "HO": 26, "TK": 23, "RB": 29, "IF": 54, "CL": 32, "CG": 51, "FF": 24, "FA": 18, "PTS": 81}}, {"Richmond": {"KI": 155, "MK": 57, "HB": 122, "DI": 277, "GL": 16, "BH": 9, "HO": 41, "TK": 52, "RB": 41, "IF": 48, "CL": 31, "CG": 50, "FF": 18, "FA": 24, "PTS": 105}, "Carlton": {"KI": 189, "MK": 69, "HB": 114, "DI": 303, "GL": 12, "BH": 9, "HO": 26, "TK": 23, "RB": 29, "IF": 54, "CL": 32, "CG": 51, "FF": 24, "FA": 18, "PTS": 81}}, {"Richmond": {"KI": 155, "MK": 57, "HB": 122, "DI": 277, "GL": 16, "BH": 9, "HO": 41, "TK": 52, "RB": 41, "IF": 48, "CL": 31, "CG": 50, "FF": 18, "FA": 24, "PTS": 105}, "Carlton": {"KI": 189, "MK": 69, "HB": 114, "DI": 303, "GL": 12, "BH": 9, "HO": 26, "TK": 23, "RB": 29, "IF": 54, "CL": 32, "CG": 51, "FF": 24, "FA": 18, "PTS": 81}}, {"Richmond": {"KI": 155, "MK": 57, "HB": 122, "DI": 277, "GL": 16, "BH": 9, "HO": 41, "TK": 52, "RB": 41, "IF": 48, "CL": 31, "CG": 50, "FF": 18, "FA": 24, "PTS": 105}, "Carlton": {"KI": 189, "MK": 69, "HB": 114, "DI": 303, "GL": 12, "BH": 9, "HO": 26, "TK": 23, "RB": 29, "IF": 54, "CL": 32, "CG": 51, "FF": 24, "FA": 18, "PTS": 81}}, {"Richmond": {"KI": 155, "MK": 57, "HB": 122, "DI": 277, "GL": 16, "BH": 9, "HO": 41, "TK": 52, "RB": 41, "IF": 48, "CL": 31, "CG": 50, "FF": 18, "FA": 24, "PTS": 105}, "Carlton": {"KI": 189, "MK": 69, "HB": 114, "DI": 303, "GL": 12, "BH": 9, "HO": 26, "TK": 23, "RB": 29, "IF": 54, "CL": 32, "CG": 51, "FF": 24, "FA": 18, "PTS": 81}}], "6": [{"Richmond": {"KI": 155, "MK": 57, "HB": 122, "DI": 277, "GL": 16, "BH": 9, "HO": 41, "TK": 52, "RB": 41, "IF": 48, "CL": 31, "CG": 50, "FF": 18, "FA": 24, "PTS": 105}, "Carlton": {"KI": 189, "MK": 69, "HB": 114, "DI": 303, "GL": 12, "BH": 9, "HO": 26, "TK": 23, "RB": 29, "IF": 54, "CL": 32, "CG": 51, "FF": 24, "FA": 18, "PTS": 81}}, {"Richmond": {"KI": 155, "MK": 57, "HB": 122, "DI": 277, "GL": 16, "BH": 9, "HO": 41, "TK": 52, "RB": 41, "IF": 48, "CL": 31, "CG": 50, "FF": 18, "FA": 24, "PTS": 105}, "Carlton": {"KI": 189, "MK": 69, "HB": 114, "DI": 303, "GL": 12, "BH": 9, "HO": 26, "TK": 23, "RB": 29, "IF": 54, "CL": 32, "CG": 51, "FF": 24, "FA": 18, "PTS": 81}}, {"Richmond": {"KI": 155, "MK": 57, "HB": 122, "DI": 277, "GL": 16, "BH": 9, "HO": 41, "TK": 52, "RB": 41, "IF": 48, "CL": 31, "CG": 50, "FF": 18, "FA": 24, "PTS": 105}, "Carlton": {"KI": 189, "MK": 69, "HB": 114, "DI": 303, "GL": 12, "BH": 9, "HO": 26, "TK": 23, "RB": 29, "IF": 54, "CL": 32, "CG": 51, "FF": 24, "FA": 18, "PTS": 81}}, {"Richmond": {"KI": 155, "MK": 57, "HB": 122, "DI": 277, "GL": 16, "BH": 9, "HO": 41, "TK": 52, "RB": 41, "IF": 48, "CL": 31, "CG": 50, "FF": 18, "FA": 24, "PTS": 105}, "Carlton": {"KI": 189, "MK": 69, "HB": 114, "DI": 303, "GL": 12, "BH": 9, "HO": 26, "TK": 23, "RB": 29, "IF": 54, "CL": 32, "CG": 51, "FF": 24, "FA": 18, "PTS": 81}}, {"Richmond": {"KI": 155, "MK": 57, "HB": 122, "DI": 277, "GL": 16, "BH": 9, "HO": 41, "TK": 52, "RB": 41, "IF": 48, "CL": 31, "CG": 50, "FF": 18, "FA": 24, "PTS": 105}, "Carlton": {"KI": 189, "MK": 69, "HB": 114, "DI": 303, "GL": 12, "BH": 9, "HO": 26, "TK": 23, "RB": 29, "IF": 54, "CL": 32, "CG": 51, "FF": 24, "FA": 18, "PTS": 81}}, {"Richmond": {"KI": 155, "MK": 57, "HB": 122, "DI": 277, "GL": 16, "BH": 9, "HO": 41, "TK": 52, "RB": 41, "IF": 48, "CL": 31, "CG": 50, "FF": 18, "FA": 24, "PTS": 105}, "Carlton": {"KI": 189, "MK": 69, "HB": 114, "DI": 303, "GL": 12, "BH": 9, "HO": 26, "TK": 23, "RB": 29, "IF": 54, "CL": 32, "CG": 51, "FF": 24, "FA": 18, "PTS": 81}}, {"Richmond": {"KI": 155, "MK": 57, "HB": 122, "DI": 277, "GL": 16, "BH": 9, "HO": 41, "TK": 52, "RB": 41, "IF": 48, "CL": 31, "CG": 50, "FF": 18, "FA": 24, "PTS": 105}, "Carlton": {"KI": 189, "MK": 69, "HB": 114, "DI": 303, "GL": 12, "BH": 9, "HO": 26, "TK": 23, "RB": 29, "IF": 54, "CL": 32, "CG": 51, "FF": 24, "FA": 18, "PTS": 81}}, {"Richmond": {"KI": 155, "MK": 57, "HB": 122, "DI": 277, "GL": 16, "BH": 9, "HO": 41, "TK": 52, "RB": 41, "IF": 48, "CL": 31, "CG": 50, "FF": 18, "FA": 24, "PTS": 105}, "Carlton": {"KI": 189, "MK": 69, "HB": 114, "DI": 303, "GL": 12, "BH": 9, "HO": 26, "TK": 23, "RB": 29, "IF": 54, "CL": 32, "CG": 51, "FF": 24, "FA": 18, "PTS": 81}}, {"Richmond": {"KI": 155, "MK": 57, "HB": 122, "DI": 277, "GL": 16, "BH": 9, "HO": 41, "TK": 52, "RB": 41, "IF": 48, "CL": 31, "CG": 50, "FF": 18, "FA": 24, "PTS": 105}, "Carlton": {"KI": 189, "MK": 69, "HB": 114, "DI": 303, "GL": 12, "BH": 9, "HO": 26, "TK": 23, "RB": 29, "IF": 54, "CL": 32, "CG": 51, "FF": 24, "FA": 18, "PTS": 81}}], "7": [{"Richmond": {"KI": 155, "MK": 57, "HB": 122, "DI": 277, "GL": 16, "BH": 9, "HO": 41, "TK": 52, "RB": 41, "IF": 48, "CL": 31, "CG": 50, "FF": 18, "FA": 24, "PTS": 105}, "Carlton": {"KI": 189, "MK": 69, "HB": 114, "DI": 303, "GL": 12, "BH": 9, "HO": 26, "TK": 23, "RB": 29, "IF": 54, "CL": 32, "CG": 51, "FF": 24, "FA": 18, "PTS": 81}}, {"Richmond": {"KI": 155, "MK": 57, "HB": 122, "DI": 277, "GL": 16, "BH": 9, "HO": 41, "TK": 52, "RB": 41, "IF": 48, "CL": 31, "CG": 50, "FF": 18, "FA": 24, "PTS": 105}, "Carlton": {"KI": 189, "MK": 69, "HB": 114, "DI": 303, "GL": 12, "BH": 9, "HO": 26, "TK": 23, "RB": 29, "IF": 54, "CL": 32, "CG": 51, "FF": 24, "FA": 18, "PTS": 81}}, {"Richmond": {"KI": 155, "MK": 57, "HB": 122, "DI": 277, "GL": 16, "BH": 9, "HO": 41, "TK": 52, "RB": 41, "IF": 48, "CL": 31, "CG": 50, "FF": 18, "FA": 24, "PTS": 105}, "Carlton": {"KI": 189, "MK": 69, "HB": 114, "DI": 303, "GL": 12, "BH": 9, "HO": 26, "TK": 23, "RB": 29, "IF": 54, "CL": 32, "CG": 51, "FF": 24, "FA": 18, "PTS": 81}}, {"Richmond": {"KI": 155, "MK": 57, "HB": 122, "DI": 277, "GL": 16, "BH": 9, "HO": 41, "TK": 52, "RB": 41, "IF": 48, "CL": 31, "CG": 50, "FF": 18, "FA": 24, "PTS": 105}, "Carlton": {"KI": 189, "MK": 69, "HB": 114, "DI": 303, "GL": 12, "BH": 9, "HO": 26, "TK": 23, "RB": 29, "IF": 54, "CL": 32, "CG": 51, "FF": 24, "FA": 18, "PTS": 81}}, {"Richmond": {"KI": 155, "MK": 57, "HB": 122, "DI": 277, "GL": 16, "BH": 9, "HO": 41, "TK": 52, "RB": 41, "IF": 48, "CL": 31, "CG": 50, "FF": 18, "FA": 24, "PTS": 105}, "Carlton": {"KI": 189, "MK": 69, "HB": 114, "DI": 303, "GL": 12, "BH": 9, "HO": 26, "TK": 23, "RB": 29, "IF": 54, "CL": 32, "CG": 51, "FF": 24, "FA": 18, "PTS": 81}}, {"Richmond": {"KI": 155, "MK": 57, "HB": 122, "DI": 277, "GL": 16, "BH": 9, "HO": 41, "TK": 52, "RB": 41, "IF": 48, "CL": 31, "CG": 50, "FF": 18, "FA": 24, "PTS": 105}, "Carlton": {"KI": 189, "MK": 69, "HB": 114, "DI": 303, "GL": 12, "BH": 9, "HO": 26, "TK": 23, "RB": 29, "IF": 54, "CL": 32, "CG": 51, "FF": 24, "FA": 18, "PTS": 81}}, {"Richmond": {"KI": 155, "MK": 57, "HB": 122, "DI": 277, "GL": 16, "BH": 9, "HO": 41, "TK": 52, "RB": 41, "IF": 48, "CL": 31, "CG": 50, "FF": 18, "FA": 24, "PTS": 105}, "Carlton": {"KI": 189, "MK": 69, "HB": 114, "DI": 303, "GL": 12, "BH": 9, "HO": 26, "TK": 23, "RB": 29, "IF": 54, "CL": 32, "CG": 51, "FF": 24, "FA": 18, "PTS": 81}}, {"Richmond": {"KI": 155, "MK": 57, "HB": 122, "DI": 277, "GL": 16, "BH": 9, "HO": 41, "TK": 52, "RB": 41, "IF": 48, "CL": 31, "CG": 50, "FF": 18, "FA": 24, "PTS": 105}, "Carlton": {"KI": 189, "MK": 69, "HB": 114, "DI": 303, "GL": 12, "BH": 9, "HO": 26, "TK": 23, "RB": 29, "IF": 54, "CL": 32, "CG": 51, "FF": 24, "FA": 18, "PTS": 81}}, {"Richmond": {"KI": 155, "MK": 57, "HB": 122, "DI": 277, "GL": 16, "BH": 9, "HO": 41, "TK": 52, "RB": 41, "IF": 48, "CL": 31, "CG": 50, "FF": 18, "FA": 24, "PTS": 105}, "Carlton": {"KI": 189, "MK": 69, "HB": 114, "DI": 303, "GL": 12, "BH": 9, "HO": 26, "TK": 23, "RB": 29, "IF": 54, "CL": 32, "CG": 51, "FF": 24, "FA": 18, "PTS": 81}}], "8": [{"Richmond": {"KI": 155, "MK": 57, "HB": 122, "DI": 277, "GL": 16, "BH": 9, "HO": 41, "TK": 52, "RB": 41, "IF": 48, "CL": 31, "CG": 50, "FF": 18, "FA": 24, "PTS": 105}, "Carlton": {"KI": 189, "MK": 69, "HB": 114, "DI": 303, "GL": 12, "BH": 9, "HO": 26, "TK": 23, "RB": 29, "IF": 54, "CL": 32, "CG": 51, "FF": 24, "FA": 18, "PTS": 81}}, {"Richmond": {"KI": 155, "MK": 57, "HB": 122, "DI": 277, "GL": 16, "BH": 9, "HO": 41, "TK": 52, "RB": 41, "IF": 48, "CL": 31, "CG": 50, "FF": 18, "FA": 24, "PTS": 105}, "Carlton": {"KI": 189, "MK": 69, "HB": 114, "DI": 303, "GL": 12, "BH": 9, "HO": 26, "TK": 23, "RB": 29, "IF": 54, "CL": 32, "CG": 51, "FF": 24, "FA": 18, "PTS": 81}}, {"Richmond": {"KI": 155, "MK": 57, "HB": 122, "DI": 277, "GL": 16, "BH": 9, "HO": 41, "TK": 52, "RB": 41, "IF": 48, "CL": 31, "CG": 50, "FF": 18, "FA": 24, "PTS": 105}, "Carlton": {"KI": 189, "MK": 69, "HB": 114, "DI": 303, "GL": 12, "BH": 9, "HO": 26, "TK": 23, "RB": 29, "IF": 54, "CL": 32, "CG": 51, "FF": 24, "FA": 18, "PTS": 81}}, {"Richmond": {"KI": 155, "MK": 57, "HB": 122, "DI": 277, "GL": 16, "BH": 9, "HO": 41, "TK": 52, "RB": 41, "IF": 48, "CL": 31, "CG": 50, "FF": 18, "FA": 24, "PTS": 105}, "Carlton": {"KI": 189, "MK": 69, "HB": 114, "DI": 303, "GL": 12, "BH": 9, "HO": 26, "TK": 23, "RB": 29, "IF": 54, "CL": 32, "CG": 51, "FF": 24, "FA": 18, "PTS": 81}}, {"Richmond": {"KI": 155, "MK": 57, "HB": 122, "DI": 277, "GL": 16, "BH": 9, "HO": 41, "TK": 52, "RB": 41, "IF": 48, "CL": 31, "CG": 50, "FF": 18, "FA": 24, "PTS": 105}, "Carlton": {"KI": 189, "MK": 69, "HB": 114, "DI": 303, "GL": 12, "BH": 9, "HO": 26, "TK": 23, "RB": 29, "IF": 54, "CL": 32, "CG": 51, "FF": 24, "FA": 18, "PTS": 81}}, {"Richmond": {"KI": 155, "MK": 57, "HB": 122, "DI": 277, "GL": 16, "BH": 9, "HO": 41, "TK": 52, "RB": 41, "IF": 48, "CL": 31, "CG": 50, "FF": 18, "FA": 24, "PTS": 105}, "Carlton": {"KI": 189, "MK": 69, "HB": 114, "DI": 303, "GL": 12, "BH": 9, "HO": 26, "TK": 23, "RB": 29, "IF": 54, "CL": 32, "CG": 51, "FF": 24, "FA": 18, "PTS": 81}}, {"Richmond": {"KI": 155, "MK": 57, "HB": 122, "DI": 277, "GL": 16, "BH": 9, "HO": 41, "TK": 52, "RB": 41, "IF": 48, "CL": 31, "CG": 50, "FF": 18, "FA": 24, "PTS": 105}, "Carlton": {"KI": 189, "MK": 69, "HB": 114, "DI": 303, "GL": 12, "BH": 9, "HO": 26, "TK": 23, "RB": 29, "IF": 54, "CL": 32, "CG": 51, "FF": 24, "FA": 18, "PTS": 81}}, {"Richmond": {"KI": 155, "MK": 57, "HB": 122, "DI": 277, "GL": 16, "BH": 9, "HO": 41, "TK": 52, "RB": 41, "IF": 48, "CL": 31, "CG": 50, "FF": 18, "FA": 24, "PTS": 105}, "Carlton": {"KI": 189, "MK": 69, "HB": 114, "DI": 303, "GL": 12, "BH": 9, "HO": 26, "TK": 23, "RB": 29, "IF": 54, "CL": 32, "CG": 51, "FF": 24, "FA": 18, "PTS": 81}}, {"Richmond": {"KI": 155, "MK": 57, "HB": 122, "DI": 277, "GL": 16, "BH": 9, "HO": 41, "TK": 52, "RB": 41, "IF": 48, "CL": 31, "CG": 50, "FF": 18, "FA": 24, "PTS": 105}, "Carlton": {"KI": 189, "MK": 69, "HB": 114, "DI": 303, "GL": 12, "BH": 9, "HO": 26, "TK": 23, "RB": 29, "IF": 54, "CL": 32, "CG": 51, "FF": 24, "FA": 18, "PTS": 81}}], "9": [{"Richmond": {"KI": 155, "MK": 57, "HB": 122, "DI": 277, "GL": 16, "BH": 9, "HO": 41, "TK": 52, "RB": 41, "IF": 48, "CL": 31, "CG": 50, "FF": 18, "FA": 24, "PTS": 105}, "Carlton": {"KI": 189, "MK": 69, "HB": 114, "DI": 303, "GL": 12, "BH": 9, "HO": 26, "TK": 23, "RB": 29, "IF": 54, "CL": 32, "CG": 51, "FF": 24, "FA": 18, "PTS": 81}}, {"Richmond": {"KI": 155, "MK": 57, "HB": 122, "DI": 277, "GL": 16, "BH": 9, "HO": 41, "TK": 52, "RB": 41, "IF": 48, "CL": 31, "CG": 50, "FF": 18, "FA": 24, "PTS": 105}, "Carlton": {"KI": 189, "MK": 69, "HB": 114, "DI": 303, "GL": 12, "BH": 9, "HO": 26, "TK": 23, "RB": 29, "IF": 54, "CL": 32, "CG": 51, "FF": 24, "FA": 18, "PTS": 81}}, {"Richmond": {"KI": 155, "MK": 57, "HB": 122, "DI": 277, "GL": 16, "BH": 9, "HO": 41, "TK": 52, "RB": 41, "IF": 48, "CL": 31, "CG": 50, "FF": 18, "FA": 24, "PTS": 105}, "Carlton": {"KI": 189, "MK": 69, "HB": 114, "DI": 303, "GL": 12, "BH": 9, "HO": 26, "TK": 23, "RB": 29, "IF": 54, "CL": 32, "CG": 51, "FF": 24, "FA": 18, "PTS": 81}}, {"Richmond": {"KI": 155, "MK": 57, "HB": 122, "DI": 277, "GL": 16, "BH": 9, "HO": 41, "TK": 52, "RB": 41, "IF": 48, "CL": 31, "CG": 50, "FF": 18, "FA": 24, "PTS": 105}, "Carlton": {"KI": 189, "MK": 69, "HB": 114, "DI": 303, "GL": 12, "BH": 9, "HO": 26, "TK": 23, "RB": 29, "IF": 54, "CL": 32, "CG": 51, "FF": 24, "FA": 18, "PTS": 81}}, {"Richmond": {"KI": 155, "MK": 57, "HB": 122, "DI": 277, "GL": 16, "BH": 9, "HO": 41, "TK": 52, "RB": 41, "IF": 48, "CL": 31, "CG": 50, "FF": 18, "FA": 24, "PTS": 105}, "Carlton": {"KI": 189, "MK": 69, "HB": 114, "DI": 303, "GL": 12, "BH": 9, "HO": 26, "TK": 23, "RB": 29, "IF": 54, "CL": 32, "CG": 51, "FF": 24, "FA": 18, "PTS": 81}}, {"Richmond": {"KI": 155, "MK": 57, "HB": 122, "DI": 277, "GL": 16, "BH": 9, "HO": 41, "TK": 52, "RB": 41, "IF": 48, "CL": 31, "CG": 50, "FF": 18, "FA": 24, "PTS": 105}, "Carlton": {"KI": 189, "MK": 69, "HB": 114, "DI": 303, "GL": 12, "BH": 9, "HO": 26, "TK": 23, "RB": 29, "IF": 54, "CL": 32, "CG": 51, "FF": 24, "FA": 18, "PTS": 81}}, {"Richmond": {"KI": 155, "MK": 57, "HB": 122, "DI": 277, "GL": 16, "BH": 9, "HO": 41, "TK": 52, "RB": 41, "IF": 48, "CL": 31, "CG": 50, "FF": 18, "FA": 24, "PTS": 105}, "Carlton": {"KI": 189, "MK": 69, "HB": 114, "DI": 303, "GL": 12, "BH": 9, "HO": 26, "TK": 23, "RB": 29, "IF": 54, "CL": 32, "CG": 51, "FF": 24, "FA": 18, "PTS": 81}}, {"Richmond": {"KI": 155, "MK": 57, "HB": 122, "DI": 277, "GL": 16, "BH": 9, "HO": 41, "TK": 52, "RB": 41, "IF": 48, "CL": 31, "CG": 50, "FF": 18, "FA": 24, "PTS": 105}, "Carlton": {"KI": 189, "MK": 69, "HB": 114, "DI": 303, "GL": 12, "BH": 9, "HO": 26, "TK": 23, "RB": 29, "IF": 54, "CL": 32, "CG": 51, "FF": 24, "FA": 18, "PTS": 81}}, {"Richmond": {"KI": 155, "MK": 57, "HB": 122, "DI": 277, "GL": 16, "BH": 9, "HO": 41, "TK": 52, "RB": 41, "IF": 48, "CL": 31, "CG": 50, "FF": 18, "FA": 24, "PTS": 105}, "Carlton": {"KI": 189, "MK": 69, "HB": 114, "DI": 303, "GL": 12, "BH": 9, "HO": 26, "TK": 23, "RB": 29, "IF": 54, "CL": 32, "CG": 51, "FF": 24, "FA": 18, "PTS": 81}}], "10": [{"Richmond": {"KI": 155, "MK": 57, "HB": 122, "DI": 277, "GL": 16, "BH": 9, "HO": 41, "TK": 52, "RB": 41, "IF": 48, "CL": 31, "CG": 50, "FF": 18, "FA": 24, "PTS": 105}, "Carlton": {"KI": 189, "MK": 69, "HB": 114, "DI": 303, "GL": 12, "BH": 9, "HO": 26, "TK": 23, "RB": 29, "IF": 54, "CL": 32, "CG": 51, "FF": 24, "FA": 18, "PTS": 81}}, {"Richmond": {"KI": 155, "MK": 57, "HB": 122, "DI": 277, "GL": 16, "BH": 9, "HO": 41, "TK": 52, "RB": 41, "IF": 48, "CL": 31, "CG": 50, "FF": 18, "FA": 24, "PTS": 105}, "Carlton": {"KI": 189, "MK": 69, "HB": 114, "DI": 303, "GL": 12, "BH": 9, "HO": 26, "TK": 23, "RB": 29, "IF": 54, "CL": 32, "CG": 51, "FF": 24, "FA": 18, "PTS": 81}}, {"Richmond": {"KI": 155, "MK": 57, "HB": 122, "DI": 277, "GL": 16, "BH": 9, "HO": 41, "TK": 52, "RB": 41, "IF": 48, "CL": 31, "CG": 50, "FF": 18, "FA": 24, "PTS": 105}, "Carlton": {"KI": 189, "MK": 69, "HB": 114, "DI": 303, "GL": 12, "BH": 9, "HO": 26, "TK": 23, "RB": 29, "IF": 54, "CL": 32, "CG": 51, "FF": 24, "FA": 18, "PTS": 81}}, {"Richmond": {"KI": 155, "MK": 57, "HB": 122, "DI": 277, "GL": 16, "BH": 9, "HO": 41, "TK": 52, "RB": 41, "IF": 48, "CL": 31, "CG": 50, "FF": 18, "FA": 24, "PTS": 105}, "Carlton": {"KI": 189, "MK": 69, "HB": 114, "DI": 303, "GL": 12, "BH": 9, "HO": 26, "TK": 23, "RB": 29, "IF": 54, "CL": 32, "CG": 51, "FF": 24, "FA": 18, "PTS": 81}}, {"Richmond": {"KI": 155, "MK": 57, "HB": 122, "DI": 277, "GL": 16, "BH": 9, "HO": 41, "TK": 52, "RB": 41, "IF": 48, "CL": 31, "CG": 50, "FF": 18, "FA": 24, "PTS": 105}, "Carlton": {"KI": 189, "MK": 69, "HB": 114, "DI": 303, "GL": 12, "BH": 9, "HO": 26, "TK": 23, "RB": 29, "IF": 54, "CL": 32, "CG": 51, "FF": 24, "FA": 18, "PTS": 81}}, {"Richmond": {"KI": 155, "MK": 57, "HB": 122, "DI": 277, "GL": 16, "BH": 9, "HO": 41, "TK": 52, "RB": 41, "IF": 48, "CL": 31, "CG": 50, "FF": 18, "FA": 24, "PTS": 105}, "Carlton": {"KI": 189, "MK": 69, "HB": 114, "DI": 303, "GL": 12, "BH": 9, "HO": 26, "TK": 23, "RB": 29, "IF": 54, "CL": 32, "CG": 51, "FF": 24, "FA": 18, "PTS": 81}}, {"Richmond": {"KI": 155, "MK": 57, "HB": 122, "DI": 277, "GL": 16, "BH": 9, "HO": 41, "TK": 52, "RB": 41, "IF": 48, "CL": 31, "CG": 50, "FF": 18, "FA": 24, "PTS": 105}, "Carlton": {"KI": 189, "MK": 69, "HB": 114, "DI": 303, "GL": 12, "BH": 9, "HO": 26, "TK": 23, "RB": 29, "IF": 54, "CL": 32, "CG": 51, "FF": 24, "FA": 18, "PTS": 81}}], "11": [{"Richmond": {"KI": 155, "MK": 57, "HB": 122, "DI": 277, "GL": 16, "BH": 9, "HO": 41, "TK": 52, "RB": 41, "IF": 48, "CL": 31, "CG": 50, "FF": 18, "FA": 24, "PTS": 105}, "Carlton": {"KI": 189, "MK": 69, "HB": 114, "DI": 303, "GL": 12, "BH": 9, "HO": 26, "TK": 23, "RB": 29, "IF": 54, "CL": 32, "CG": 51, "FF": 24, "FA": 18, "PTS": 81}}, {"Richmond": {"KI": 155, "MK": 57, "HB": 122, "DI": 277, "GL": 16, "BH": 9, "HO": 41, "TK": 52, "RB": 41, "IF": 48, "CL": 31, "CG": 50, "FF": 18, "FA": 24, "PTS": 105}, "Carlton": {"KI": 189, "MK": 69, "HB": 114, "DI": 303, "GL": 12, "BH": 9, "HO": 26, "TK": 23, "RB": 29, "IF": 54, "CL": 32, "CG": 51, "FF": 24, "FA": 18, "PTS": 81}}, {"Richmond": {"KI": 155, "MK": 57, "HB": 122, "DI": 277, "GL": 16, "BH": 9, "HO": 41, "TK": 52, "RB": 41, "IF": 48, "CL": 31, "CG": 50, "FF": 18, "FA": 24, "PTS": 105}, "Carlton": {"KI": 189, "MK": 69, "HB": 114, "DI": 303, "GL": 12, "BH": 9, "HO": 26, "TK": 23, "RB": 29, "IF": 54, "CL": 32, "CG": 51, "FF": 24, "FA": 18, "PTS": 81}}, {"Richmond": {"KI": 155, "MK": 57, "HB": 122, "DI": 277, "GL": 16, "BH": 9, "HO": 41, "TK": 52, "RB": 41, "IF": 48, "CL": 31, "CG": 50, "FF": 18, "FA": 24, "PTS": 105}, "Carlton": {"KI": 189, "MK": 69, "HB": 114, "DI": 303, "GL": 12, "BH": 9, "HO": 26, "TK": 23, "RB": 29, "IF": 54, "CL": 32, "CG": 51, "FF": 24, "FA": 18, "PTS": 81}}, {"Richmond": {"KI": 155, "MK": 57, "HB": 122, "DI": 277, "GL": 16, "BH": 9, "HO": 41, "TK": 52, "RB": 41, "IF": 48, "CL": 31, "CG": 50, "FF": 18, "FA": 24, "PTS": 105}, "Carlton": {"KI": 189, "MK": 69, "HB": 114, "DI": 303, "GL": 12, "BH": 9, "HO": 26, "TK": 23, "RB": 29, "IF": 54, "CL": 32, "CG": 51, "FF": 24, "FA": 18, "PTS": 81}}, {"Richmond": {"KI": 155, "MK": 57, "HB": 122, "DI": 277, "GL": 16, "BH": 9, "HO": 41, "TK": 52, "RB": 41, "IF": 48, "CL": 31, "CG": 50, "FF": 18, "FA": 24, "PTS": 105}, "Carlton": {"KI": 189, "MK": 69, "HB": 114, "DI": 303, "GL": 12, "BH": 9, "HO": 26, "TK": 23, "RB": 29, "IF": 54, "CL": 32, "CG": 51, "FF": 24, "FA": 18, "PTS": 81}}, {"Richmond": {"KI": 155, "MK": 57, "HB": 122, "DI": 277, "GL": 16, "BH": 9, "HO": 41, "TK": 52, "RB": 41, "IF": 48, "CL": 31, "CG": 50, "FF": 18, "FA": 24, "PTS": 105}, "Carlton": {"KI": 189, "MK": 69, "HB": 114, "DI": 303, "GL": 12, "BH": 9, "HO": 26, "TK": 23, "RB": 29, "IF": 54, "CL": 32, "CG": 51, "FF": 24, "FA": 18, "PTS": 81}}, {"Richmond": {"KI": 155, "MK": 57, "HB": 122, "DI": 277, "GL": 16, "BH": 9, "HO": 41, "TK": 52, "RB": 41, "IF": 48, "CL": 31, "CG": 50, "FF": 18, "FA": 24, "PTS": 105}, "Carlton": {"KI": 189, "MK": 69, "HB": 114, "DI": 303, "GL": 12, "BH": 9, "HO": 26, "TK": 23, "RB": 29, "IF": 54, "CL": 32, "CG": 51, "FF": 24, "FA": 18, "PTS": 81}}], "12": [{"Richmond": {"KI": 155, "MK": 57, "HB": 122, "DI": 277, "GL": 16, "BH": 9, "HO": 41, "TK": 52, "RB": 41, "IF": 48, "CL": 31, "CG": 50, "FF": 18, "FA": 24, "PTS": 105}, "Carlton": {"KI": 189, "MK": 69, "HB": 114, "DI": 303, "GL": 12, "BH": 9, "HO": 26, "TK": 23, "RB": 29, "IF": 54, "CL": 32, "CG": 51, "FF": 24, "FA": 18, "PTS": 81}}, {"Richmond": {"KI": 155, "MK": 57, "HB": 122, "DI": 277, "GL": 16, "BH": 9, "HO": 41, "TK": 52, "RB": 41, "IF": 48, "CL": 31, "CG": 50, "FF": 18, "FA": 24, "PTS": 105}, "Carlton": {"KI": 189, "MK": 69, "HB": 114, "DI": 303, "GL": 12, "BH": 9, "HO": 26, "TK": 23, "RB": 29, "IF": 54, "CL": 32, "CG": 51, "FF": 24, "FA": 18, "PTS": 81}}, {"Richmond": {"KI": 155, "MK": 57, "HB": 122, "DI": 277, "GL": 16, "BH": 9, "HO": 41, "TK": 52, "RB": 41, "IF": 48, "CL": 31, "CG": 50, "FF": 18, "FA": 24, "PTS": 105}, "Carlton": {"KI": 189, "MK": 69, "HB": 114, "DI": 303, "GL": 12, "BH": 9, "HO": 26, "TK": 23, "RB": 29, "IF": 54, "CL": 32, "CG": 51, "FF": 24, "FA": 18, "PTS": 81}}, {"Richmond": {"KI": 155, "MK": 57, "HB": 122, "DI": 277, "GL": 16, "BH": 9, "HO": 41, "TK": 52, "RB": 41, "IF": 48, "CL": 31, "CG": 50, "FF": 18, "FA": 24, "PTS": 105}, "Carlton": {"KI": 189, "MK": 69, "HB": 114, "DI": 303, "GL": 12, "BH": 9, "HO": 26, "TK": 23, "RB": 29, "IF": 54, "CL": 32, "CG": 51, "FF": 24, "FA": 18, "PTS": 81}}, {"Richmond": {"KI": 155, "MK": 57, "HB": 122, "DI": 277, "GL": 16, "BH": 9, "HO": 41, "TK": 52, "RB": 41, "IF": 48, "CL": 31, "CG": 50, "FF": 18, "FA": 24, "PTS": 105}, "Carlton": {"KI": 189, "MK": 69, "HB": 114, "DI": 303, "GL": 12, "BH": 9, "HO": 26, "TK": 23, "RB": 29, "IF": 54, "CL": 32, "CG": 51, "FF": 24, "FA": 18, "PTS": 81}}, {"Richmond": {"KI": 155, "MK": 57, "HB": 122, "DI": 277, "GL": 16, "BH": 9, "HO": 41, "TK": 52, "RB": 41, "IF": 48, "CL": 31, "CG": 50, "FF": 18, "FA": 24, "PTS": 105}, "Carlton": {"KI": 189, "MK": 69, "HB": 114, "DI": 303, "GL": 12, "BH": 9, "HO": 26, "TK": 23, "RB": 29, "IF": 54, "CL": 32, "CG": 51, "FF": 24, "FA": 18, "PTS": 81}}, {"Richmond": {"KI": 155, "MK": 57, "HB": 122, "DI": 277, "GL": 16, "BH": 9, "HO": 41, "TK": 52, "RB": 41, "IF": 48, "CL": 31, "CG": 50, "FF": 18, "FA": 24, "PTS": 105}, "Carlton": {"KI": 189, "MK": 69, "HB": 114, "DI": 303, "GL": 12, "BH": 9, "HO": 26, "TK": 23, "RB": 29, "IF": 54, "CL": 32, "CG": 51, "FF": 24, "FA": 18, "PTS": 81}}, {"Richmond": {"KI": 155, "MK": 57, "HB": 122, "DI": 277, "GL": 16, "BH": 9, "HO": 41, "TK": 52, "RB": 41, "IF": 48, "CL": 31, "CG": 50, "FF": 18, "FA": 24, "PTS": 105}, "Carlton": {"KI": 189, "MK": 69, "HB": 114, "DI": 303, "GL": 12, "BH": 9, "HO": 26, "TK": 23, "RB": 29, "IF": 54, "CL": 32, "CG": 51, "FF": 24, "FA": 18, "PTS": 81}}, {"Richmond": {"KI": 155, "MK": 57, "HB": 122, "DI": 277, "GL": 16, "BH": 9, "HO": 41, "TK": 52, "RB": 41, "IF": 48, "CL": 31, "CG": 50, "FF": 18, "FA": 24, "PTS": 105}, "Carlton": {"KI": 189, "MK": 69, "HB": 114, "DI": 303, "GL": 12, "BH": 9, "HO": 26, "TK": 23, "RB": 29, "IF": 54, "CL": 32, "CG": 51, "FF": 24, "FA": 18, "PTS": 81}}], "13": [{"Richmond": {"KI": 155, "MK": 57, "HB": 122, "DI": 277, "GL": 16, "BH": 9, "HO": 41, "TK": 52, "RB": 41, "IF": 48, "CL": 31, "CG": 50, "FF": 18, "FA": 24, "PTS": 105}, "Carlton": {"KI": 189, "MK": 69, "HB": 114, "DI": 303, "GL": 12, "BH": 9, "HO": 26, "TK": 23, "RB": 29, "IF": 54, "CL": 32, "CG": 51, "FF": 24, "FA": 18, "PTS": 81}}, {"Richmond": {"KI": 155, "MK": 57, "HB": 122, "DI": 277, "GL": 16, "BH": 9, "HO": 41, "TK": 52, "RB": 41, "IF": 48, "CL": 31, "CG": 50, "FF": 18, "FA": 24, "PTS": 105}, "Carlton": {"KI": 189, "MK": 69, "HB": 114, "DI": 303, "GL": 12, "BH": 9, "HO": 26, "TK": 23, "RB": 29, "IF": 54, "CL": 32, "CG": 51, "FF": 24, "FA": 18, "PTS": 81}}, {"Richmond": {"KI": 155, "MK": 57, "HB": 122, "DI": 277, "GL": 16, "BH": 9, "HO": 41, "TK": 52, "RB": 41, "IF": 48, "CL": 31, "CG": 50, "FF": 18, "FA": 24, "PTS": 105}, "Carlton": {"KI": 189, "MK": 69, "HB": 114, "DI": 303, "GL": 12, "BH": 9, "HO": 26, "TK": 23, "RB": 29, "IF": 54, "CL": 32, "CG": 51, "FF": 24, "FA": 18, "PTS": 81}}, {"Richmond": {"KI": 155, "MK": 57, "HB": 122, "DI": 277, "GL": 16, "BH": 9, "HO": 41, "TK": 52, "RB": 41, "IF": 48, "CL": 31, "CG": 50, "FF": 18, "FA": 24, "PTS": 105}, "Carlton": {"KI": 189, "MK": 69, "HB": 114, "DI": 303, "GL": 12, "BH": 9, "HO": 26, "TK": 23, "RB": 29, "IF": 54, "CL": 32, "CG": 51, "FF": 24, "FA": 18, "PTS": 81}}, {"Richmond": {"KI": 155, "MK": 57, "HB": 122, "DI": 277, "GL": 16, "BH": 9, "HO": 41, "TK": 52, "RB": 41, "IF": 48, "CL": 31, "CG": 50, "FF": 18, "FA": 24, "PTS": 105}, "Carlton": {"KI": 189, "MK": 69, "HB": 114, "DI": 303, "GL": 12, "BH": 9, "HO": 26, "TK": 23, "RB": 29, "IF": 54, "CL": 32, "CG": 51, "FF": 24, "FA": 18, "PTS": 81}}, {"Richmond": {"KI": 155, "MK": 57, "HB": 122, "DI": 277, "GL": 16, "BH": 9, "HO": 41, "TK": 52, "RB": 41, "IF": 48, "CL": 31, "CG": 50, "FF": 18, "FA": 24, "PTS": 105}, "Carlton": {"KI": 189, "MK": 69, "HB": 114, "DI": 303, "GL": 12, "BH": 9, "HO": 26, "TK": 23, "RB": 29, "IF": 54, "CL": 32, "CG": 51, "FF": 24, "FA": 18, "PTS": 81}}, {"Richmond": {"KI": 155, "MK": 57, "HB": 122, "DI": 277, "GL": 16, "BH": 9, "HO": 41, "TK": 52, "RB": 41, "IF": 48, "CL": 31, "CG": 50, "FF": 18, "FA": 24, "PTS": 105}, "Carlton": {"KI": 189, "MK": 69, "HB": 114, "DI": 303, "GL": 12, "BH": 9, "HO": 26, "TK": 23, "RB": 29, "IF": 54, "CL": 32, "CG": 51, "FF": 24, "FA": 18, "PTS": 81}}, {"Richmond": {"KI": 155, "MK": 57, "HB": 122, "DI": 277, "GL": 16, "BH": 9, "HO": 41, "TK": 52, "RB": 41, "IF": 48, "CL": 31, "CG": 50, "FF": 18, "FA": 24, "PTS": 105}, "Carlton": {"KI": 189, "MK": 69, "HB": 114, "DI": 303, "GL": 12, "BH": 9, "HO": 26, "TK": 23, "RB": 29, "IF": 54, "CL": 32, "CG": 51, "FF": 24, "FA": 18, "PTS": 81}}, {"Richmond": {"KI": 155, "MK": 57, "HB": 122, "DI": 277, "GL": 16, "BH": 9, "HO": 41, "TK": 52, "RB": 41, "IF": 48, "CL": 31, "CG": 50, "FF": 18, "FA": 24, "PTS": 105}, "Carlton": {"KI": 189, "MK": 69, "HB": 114, "DI": 303, "GL": 12, "BH": 9, "HO": 26, "TK": 23, "RB": 29, "IF": 54, "CL": 32, "CG": 51, "FF": 24, "FA": 18, "PTS": 81}}], "14": [{"Richmond": {"KI": 155, "MK": 57, "HB": 122, "DI": 277, "GL": 16, "BH": 9, "HO": 41, "TK": 52, "RB": 41, "IF": 48, "CL": 31, "CG": 50, "FF": 18, "FA": 24, "PTS": 105}, "Carlton": {"KI": 189, "MK": 69, "HB": 114, "DI": 303, "GL": 12, "BH": 9, "HO": 26, "TK": 23, "RB": 29, "IF": 54, "CL": 32, "CG": 51, "FF": 24, "FA": 18, "PTS": 81}}, {"Richmond": {"KI": 155, "MK": 57, "HB": 122, "DI": 277, "GL": 16, "BH": 9, "HO": 41, "TK": 52, "RB": 41, "IF": 48, "CL": 31, "CG": 50, "FF": 18, "FA": 24, "PTS": 105}, "Carlton": {"KI": 189, "MK": 69, "HB": 114, "DI": 303, "GL": 12, "BH": 9, "HO": 26, "TK": 23, "RB": 29, "IF": 54, "CL": 32, "CG": 51, "FF": 24, "FA": 18, "PTS": 81}}, {"Richmond": {"KI": 155, "MK": 57, "HB": 122, "DI": 277, "GL": 16, "BH": 9, "HO": 41, "TK": 52, "RB": 41, "IF": 48, "CL": 31, "CG": 50, "FF": 18, "FA": 24, "PTS": 105}, "Carlton": {"KI": 189, "MK": 69, "HB": 114, "DI": 303, "GL": 12, "BH": 9, "HO": 26, "TK": 23, "RB": 29, "IF": 54, "CL": 32, "CG": 51, "FF": 24, "FA": 18, "PTS": 81}}, {"Richmond": {"KI": 155, "MK": 57, "HB": 122, "DI": 277, "GL": 16, "BH": 9, "HO": 41, "TK": 52, "RB": 41, "IF": 48, "CL": 31, "CG": 50, "FF": 18, "FA": 24, "PTS": 105}, "Carlton": {"KI": 189, "MK": 69, "HB": 114, "DI": 303, "GL": 12, "BH": 9, "HO": 26, "TK": 23, "RB": 29, "IF": 54, "CL": 32, "CG": 51, "FF": 24, "FA": 18, "PTS": 81}}, {"Richmond": {"KI": 155, "MK": 57, "HB": 122, "DI": 277, "GL": 16, "BH": 9, "HO": 41, "TK": 52, "RB": 41, "IF": 48, "CL": 31, "CG": 50, "FF": 18, "FA": 24, "PTS": 105}, "Carlton": {"KI": 189, "MK": 69, "HB": 114, "DI": 303, "GL": 12, "BH": 9, "HO": 26, "TK": 23, "RB": 29, "IF": 54, "CL": 32, "CG": 51, "FF": 24, "FA": 18, "PTS": 81}}, {"Richmond": {"KI": 155, "MK": 57, "HB": 122, "DI": 277, "GL": 16, "BH": 9, "HO": 41, "TK": 52, "RB": 41, "IF": 48, "CL": 31, "CG": 50, "FF": 18, "FA": 24, "PTS": 105}, "Carlton": {"KI": 189, "MK": 69, "HB": 114, "DI": 303, "GL": 12, "BH": 9, "HO": 26, "TK": 23, "RB": 29, "IF": 54, "CL": 32, "CG": 51, "FF": 24, "FA": 18, "PTS": 81}}, {"Richmond": {"KI": 155, "MK": 57, "HB": 122, "DI": 277, "GL": 16, "BH": 9, "HO": 41, "TK": 52, "RB": 41, "IF": 48, "CL": 31, "CG": 50, "FF": 18, "FA": 24, "PTS": 105}, "Carlton": {"KI": 189, "MK": 69, "HB": 114, "DI": 303, "GL": 12, "BH": 9, "HO": 26, "TK": 23, "RB": 29, "IF": 54, "CL": 32, "CG": 51, "FF": 24, "FA": 18, "PTS": 81}}, {"Richmond": {"KI": 155, "MK": 57, "HB": 122, "DI": 277, "GL": 16, "BH": 9, "HO": 41, "TK": 52, "RB": 41, "IF": 48, "CL": 31, "CG": 50, "FF": 18, "FA": 24, "PTS": 105}, "Carlton": {"KI": 189, "MK": 69, "HB": 114, "DI": 303, "GL": 12, "BH": 9, "HO": 26, "TK": 23, "RB": 29, "IF": 54, "CL": 32, "CG": 51, "FF": 24, "FA": 18, "PTS": 81}}], "15": [{"Richmond": {"KI": 155, "MK": 57, "HB": 122, "DI": 277, "GL": 16, "BH": 9, "HO": 41, "TK": 52, "RB": 41, "IF": 48, "CL": 31, "CG": 50, "FF": 18, "FA": 24, "PTS": 105}, "Carlton": {"KI": 189, "MK": 69, "HB": 114, "DI": 303, "GL": 12, "BH": 9, "HO": 26, "TK": 23, "RB": 29, "IF": 54, "CL": 32, "CG": 51, "FF": 24, "FA": 18, "PTS": 81}}, {"Richmond": {"KI": 155, "MK": 57, "HB": 122, "DI": 277, "GL": 16, "BH": 9, "HO": 41, "TK": 52, "RB": 41, "IF": 48, "CL": 31, "CG": 50, "FF": 18, "FA": 24, "PTS": 105}, "Carlton": {"KI": 189, "MK": 69, "HB": 114, "DI": 303, "GL": 12, "BH": 9, "HO": 26, "TK": 23, "RB": 29, "IF": 54, "CL": 32, "CG": 51, "FF": 24, "FA": 18, "PTS": 81}}, {"Richmond": {"KI": 155, "MK": 57, "HB": 122, "DI": 277, "GL": 16, "BH": 9, "HO": 41, "TK": 52, "RB": 41, "IF": 48, "CL": 31, "CG": 50, "FF": 18, "FA": 24, "PTS": 105}, "Carlton": {"KI": 189, "MK": 69, "HB": 114, "DI": 303, "GL": 12, "BH": 9, "HO": 26, "TK": 23, "RB": 29, "IF": 54, "CL": 32, "CG": 51, "FF": 24, "FA": 18, "PTS": 81}}, {"Richmond": {"KI": 155, "MK": 57, "HB": 122, "DI": 277, "GL": 16, "BH": 9, "HO": 41, "TK": 52, "RB": 41, "IF": 48, "CL": 31, "CG": 50, "FF": 18, "FA": 24, "PTS": 105}, "Carlton": {"KI": 189, "MK": 69, "HB": 114, "DI": 303, "GL": 12, "BH": 9, "HO": 26, "TK": 23, "RB": 29, "IF": 54, "CL": 32, "CG": 51, "FF": 24, "FA": 18, "PTS": 81}}, {"Richmond": {"KI": 155, "MK": 57, "HB": 122, "DI": 277, "GL": 16, "BH": 9, "HO": 41, "TK": 52, "RB": 41, "IF": 48, "CL": 31, "CG": 50, "FF": 18, "FA": 24, "PTS": 105}, "Carlton": {"KI": 189, "MK": 69, "HB": 114, "DI": 303, "GL": 12, "BH": 9, "HO": 26, "TK": 23, "RB": 29, "IF": 54, "CL": 32, "CG": 51, "FF": 24, "FA": 18, "PTS": 81}}, {"Richmond": {"KI": 155, "MK": 57, "HB": 122, "DI": 277, "GL": 16, "BH": 9, "HO": 41, "TK": 52, "RB": 41, "IF": 48, "CL": 31, "CG": 50, "FF": 18, "FA": 24, "PTS": 105}, "Carlton": {"KI": 189, "MK": 69, "HB": 114, "DI": 303, "GL": 12, "BH": 9, "HO": 26, "TK": 23, "RB": 29, "IF": 54, "CL": 32, "CG": 51, "FF": 24, "FA": 18, "PTS": 81}}], "16": [{"Richmond": {"KI": 155, "MK": 57, "HB": 122, "DI": 277, "GL": 16, "BH": 9, "HO": 41, "TK": 52, "RB": 41, "IF": 48, "CL": 31, "CG": 50, "FF": 18, "FA": 24, "PTS": 105}, "Carlton": {"KI": 189, "MK": 69, "HB": 114, "DI": 303, "GL": 12, "BH": 9, "HO": 26, "TK": 23, "RB": 29, "IF": 54, "CL": 32, "CG": 51, "FF": 24, "FA": 18, "PTS": 81}}, {"Richmond": {"KI": 155, "MK": 57, "HB": 122, "DI": 277, "GL": 16, "BH": 9, "HO": 41, "TK": 52, "RB": 41, "IF": 48, "CL": 31, "CG": 50, "FF": 18, "FA": 24, "PTS": 105}, "Carlton": {"KI": 189, "MK": 69, "HB": 114, "DI": 303, "GL": 12, "BH": 9, "HO": 26, "TK": 23, "RB": 29, "IF": 54, "CL": 32, "CG": 51, "FF": 24, "FA": 18, "PTS": 81}}, {"Richmond": {"KI": 155, "MK": 57, "HB": 122, "DI": 277, "GL": 16, "BH": 9, "HO": 41, "TK": 52, "RB": 41, "IF": 48, "CL": 31, "CG": 50, "FF": 18, "FA": 24, "PTS": 105}, "Carlton": {"KI": 189, "MK": 69, "HB": 114, "DI": 303, "GL": 12, "BH": 9, "HO": 26, "TK": 23, "RB": 29, "IF": 54, "CL": 32, "CG": 51, "FF": 24, "FA": 18, "PTS": 81}}, {"Richmond": {"KI": 155, "MK": 57, "HB": 122, "DI": 277, "GL": 16, "BH": 9, "HO": 41, "TK": 52, "RB": 41, "IF": 48, "CL": 31, "CG": 50, "FF": 18, "FA": 24, "PTS": 105}, "Carlton": {"KI": 189, "MK": 69, "HB": 114, "DI": 303, "GL": 12, "BH": 9, "HO": 26, "TK": 23, "RB": 29, "IF": 54, "CL": 32, "CG": 51, "FF": 24, "FA": 18, "PTS": 81}}, {"Richmond": {"KI": 155, "MK": 57, "HB": 122, "DI": 277, "GL": 16, "BH": 9, "HO": 41, "TK": 52, "RB": 41, "IF": 48, "CL": 31, "CG": 50, "FF": 18, "FA": 24, "PTS": 105}, "Carlton": {"KI": 189, "MK": 69, "HB": 114, "DI": 303, "GL": 12, "BH": 9, "HO": 26, "TK": 23, "RB": 29, "IF": 54, "CL": 32, "CG": 51, "FF": 24, "FA": 18, "PTS": 81}}, {"Richmond": {"KI": 155, "MK": 57, "HB": 122, "DI": 277, "GL": 16, "BH": 9, "HO": 41, "TK": 52, "RB": 41, "IF": 48, "CL": 31, "CG": 50, "FF": 18, "FA": 24, "PTS": 105}, "Carlton": {"KI": 189, "MK": 69, "HB": 114, "DI": 303, "GL": 12, "BH": 9, "HO": 26, "TK": 23, "RB": 29, "IF": 54, "CL": 32, "CG": 51, "FF": 24, "FA": 18, "PTS": 81}}, {"Richmond": {"KI": 155, "MK": 57, "HB": 122, "DI": 277, "GL": 16, "BH": 9, "HO": 41, "TK": 52, "RB": 41, "IF": 48, "CL": 31, "CG": 50, "FF": 18, "FA": 24, "PTS": 105}, "Carlton": {"KI": 189, "MK": 69, "HB": 114, "DI": 303, "GL": 12, "BH": 9, "HO": 26, "TK": 23, "RB": 29, "IF": 54, "CL": 32, "CG": 51, "FF": 24, "FA": 18, "PTS": 81}}, {"Richmond": {"KI": 155, "MK": 57, "HB": 122, "DI": 277, "GL": 16, "BH": 9, "HO": 41, "TK": 52, "RB": 41, "IF": 48, "CL": 31, "CG": 50, "FF": 18, "FA": 24, "PTS": 105}, "Carlton": {"KI": 189, "MK": 69, "HB": 114, "DI": 303, "GL": 12, "BH": 9, "HO": 26, "TK": 23, "RB": 29, "IF": 54, "CL": 32, "CG": 51, "FF": 24, "FA": 18, "PTS": 81}}], "17": [{"Richmond": {"KI": 155, "MK": 57, "HB": 122, "DI": 277, "GL": 16, "BH": 9, "HO": 41, "TK": 52, "RB": 41, "IF": 48, "CL": 31, "CG": 50, "FF": 18, "FA": 24, "PTS": 105}, "Carlton": {"KI": 189, "MK": 69, "HB": 114, "DI": 303, "GL": 12, "BH": 9, "HO": 26, "TK": 23, "RB": 29, "IF": 54, "CL": 32, "CG": 51, "FF": 24, "FA": 18, "PTS": 81}}, {"Richmond": {"KI": 155, "MK": 57, "HB": 122, "DI": 277, "GL": 16, "BH": 9, "HO": 41, "TK": 52, "RB": 41, "IF": 48, "CL": 31, "CG": 50, "FF": 18, "FA": 24, "PTS": 105}, "Carlton": {"KI": 189, "MK": 69, "HB": 114, "DI": 303, "GL": 12, "BH": 9, "HO": 26, "TK": 23, "RB": 29, "IF": 54, "CL": 32, "CG": 51, "FF": 24, "FA": 18, "PTS": 81}}, {"Richmond": {"KI": 155, "MK": 57, "HB": 122, "DI": 277, "GL": 16, "BH": 9, "HO": 41, "TK": 52, "RB": 41, "IF": 48, "CL": 31, "CG": 50, "FF": 18, "FA": 24, "PTS": 105}, "Carlton": {"KI": 189, "MK": 69, "HB": 114, "DI": 303, "GL": 12, "BH": 9, "HO": 26, "TK": 23, "RB": 29, "IF": 54, "CL": 32, "CG": 51, "FF": 24, "FA": 18, "PTS": 81}}, {"Richmond": {"KI": 155, "MK": 57, "HB": 122, "DI": 277, "GL": 16, "BH": 9, "HO": 41, "TK": 52, "RB": 41, "IF": 48, "CL": 31, "CG": 50, "FF": 18, "FA": 24, "PTS": 105}, "Carlton": {"KI": 189, "MK": 69, "HB": 114, "DI": 303, "GL": 12, "BH": 9, "HO": 26, "TK": 23, "RB": 29, "IF": 54, "CL": 32, "CG": 51, "FF": 24, "FA": 18, "PTS": 81}}, {"Richmond": {"KI": 155, "MK": 57, "HB": 122, "DI": 277, "GL": 16, "BH": 9, "HO": 41, "TK": 52, "RB": 41, "IF": 48, "CL": 31, "CG": 50, "FF": 18, "FA": 24, "PTS": 105}, "Carlton": {"KI": 189, "MK": 69, "HB": 114, "DI": 303, "GL": 12, "BH": 9, "HO": 26, "TK": 23, "RB": 29, "IF": 54, "CL": 32, "CG": 51, "FF": 24, "FA": 18, "PTS": 81}}, {"Richmond": {"KI": 155, "MK": 57, "HB": 122, "DI": 277, "GL": 16, "BH": 9, "HO": 41, "TK": 52, "RB": 41, "IF": 48, "CL": 31, "CG": 50, "FF": 18, "FA": 24, "PTS": 105}, "Carlton": {"KI": 189, "MK": 69, "HB": 114, "DI": 303, "GL": 12, "BH": 9, "HO": 26, "TK": 23, "RB": 29, "IF": 54, "CL": 32, "CG": 51, "FF": 24, "FA": 18, "PTS": 81}}, {"Richmond": {"KI": 155, "MK": 57, "HB": 122, "DI": 277, "GL": 16, "BH": 9, "HO": 41, "TK": 52, "RB": 41, "IF": 48, "CL": 31, "CG": 50, "FF": 18, "FA": 24, "PTS": 105}, "Carlton": {"KI": 189, "MK": 69, "HB": 114, "DI": 303, "GL": 12, "BH": 9, "HO": 26, "TK": 23, "RB": 29, "IF": 54, "CL": 32, "CG": 51, "FF": 24, "FA": 18, "PTS": 81}}, {"Richmond": {"KI": 155, "MK": 57, "HB": 122, "DI": 277, "GL": 16, "BH": 9, "HO": 41, "TK": 52, "RB": 41, "IF": 48, "CL": 31, "CG": 50, "FF": 18, "FA": 24, "PTS": 105}, "Carlton": {"KI": 189, "MK": 69, "HB": 114, "DI": 303, "GL": 12, "BH": 9, "HO": 26, "TK": 23, "RB": 29, "IF": 54, "CL": 32, "CG": 51, "FF": 24, "FA": 18, "PTS": 81}}, {"Richmond": {"KI": 155, "MK": 57, "HB": 122, "DI": 277, "GL": 16, "BH": 9, "HO": 41, "TK": 52, "RB": 41, "IF": 48, "CL": 31, "CG": 50, "FF": 18, "FA": 24, "PTS": 105}, "Carlton": {"KI": 189, "MK": 69, "HB": 114, "DI": 303, "GL": 12, "BH": 9, "HO": 26, "TK": 23, "RB": 29, "IF": 54, "CL": 32, "CG": 51, "FF": 24, "FA": 18, "PTS": 81}}], "18": [{"Richmond": {"KI": 155, "MK": 57, "HB": 122, "DI": 277, "GL": 16, "BH": 9, "HO": 41, "TK": 52, "RB": 41, "IF": 48, "CL": 31, "CG": 50, "FF": 18, "FA": 24, "PTS": 105}, "Carlton": {"KI": 189, "MK": 69, "HB": 114, "DI": 303, "GL": 12, "BH": 9, "HO": 26, "TK": 23, "RB": 29, "IF": 54, "CL": 32, "CG": 51, "FF": 24, "FA": 18, "PTS": 81}}, {"Richmond": {"KI": 155, "MK": 57, "HB": 122, "DI": 277, "GL": 16, "BH": 9, "HO": 41, "TK": 52, "RB": 41, "IF": 48, "CL": 31, "CG": 50, "FF": 18, "FA": 24, "PTS": 105}, "Carlton": {"KI": 189, "MK": 69, "HB": 114, "DI": 303, "GL": 12, "BH": 9, "HO": 26, "TK": 23, "RB": 29, "IF": 54, "CL": 32, "CG": 51, "FF": 24, "FA": 18, "PTS": 81}}, {"Richmond": {"KI": 155, "MK": 57, "HB": 122, "DI": 277, "GL": 16, "BH": 9, "HO": 41, "TK": 52, "RB": 41, "IF": 48, "CL": 31, "CG": 50, "FF": 18, "FA": 24, "PTS": 105}, "Carlton": {"KI": 189, "MK": 69, "HB": 114, "DI": 303, "GL": 12, "BH": 9, "HO": 26, "TK": 23, "RB": 29, "IF": 54, "CL": 32, "CG": 51, "FF": 24, "FA": 18, "PTS": 81}}, {"Richmond": {"KI": 155, "MK": 57, "HB": 122, "DI": 277, "GL": 16, "BH": 9, "HO": 41, "TK": 52, "RB": 41, "IF": 48, "CL": 31, "CG": 50, "FF": 18, "FA": 24, "PTS": 105}, "Carlton": {"KI": 189, "MK": 69, "HB": 114, "DI": 303, "GL": 12, "BH": 9, "HO": 26, "TK": 23, "RB": 29, "IF": 54, "CL": 32, "CG": 51, "FF": 24, "FA": 18, "PTS": 81}}, {"Richmond": {"KI": 155, "MK": 57, "HB": 122, "DI": 277, "GL": 16, "BH": 9, "HO": 41, "TK": 52, "RB": 41, "IF": 48, "CL": 31, "CG": 50, "FF": 18, "FA": 24, "PTS": 105}, "Carlton": {"KI": 189, "MK": 69, "HB": 114, "DI": 303, "GL": 12, "BH": 9, "HO": 26, "TK": 23, "RB": 29, "IF": 54, "CL": 32, "CG": 51, "FF": 24, "FA": 18, "PTS": 81}}, {"Richmond": {"KI": 155, "MK": 57, "HB": 122, "DI": 277, "GL": 16, "BH": 9, "HO": 41, "TK": 52, "RB": 41, "IF": 48, "CL": 31, "CG": 50, "FF": 18, "FA": 24, "PTS": 105}, "Carlton": {"KI": 189, "MK": 69, "HB": 114, "DI": 303, "GL": 12, "BH": 9, "HO": 26, "TK": 23, "RB": 29, "IF": 54, "CL": 32, "CG": 51, "FF": 24, "FA": 18, "PTS": 81}}, {"Richmond": {"KI": 155, "MK": 57, "HB": 122, "DI": 277, "GL": 16, "BH": 9, "HO": 41, "TK": 52, "RB": 41, "IF": 48, "CL": 31, "CG": 50, "FF": 18, "FA": 24, "PTS": 105}, "Carlton": {"KI": 189, "MK": 69, "HB": 114, "DI": 303, "GL": 12, "BH": 9, "HO": 26, "TK": 23, "RB": 29, "IF": 54, "CL": 32, "CG": 51, "FF": 24, "FA": 18, "PTS": 81}}, {"Richmond": {"KI": 155, "MK": 57, "HB": 122, "DI": 277, "GL": 16, "BH": 9, "HO": 41, "TK": 52, "RB": 41, "IF": 48, "CL": 31, "CG": 50, "FF": 18, "FA": 24, "PTS": 105}, "Carlton": {"KI": 189, "MK": 69, "HB": 114, "DI": 303, "GL": 12, "BH": 9, "HO": 26, "TK": 23, "RB": 29, "IF": 54, "CL": 32, "CG": 51, "FF": 24, "FA": 18, "PTS": 81}}, {"Richmond": {"KI": 155, "MK": 57, "HB": 122, "DI": 277, "GL": 16, "BH": 9, "HO": 41, "TK": 52, "RB": 41, "IF": 48, "CL": 31, "CG": 50, "FF": 18, "FA": 24, "PTS": 105}, "Carlton": {"KI": 189, "MK": 69, "HB": 114, "DI": 303, "GL": 12, "BH": 9, "HO": 26, "TK": 23, "RB": 29, "IF": 54, "CL": 32, "CG": 51, "FF": 24, "FA": 18, "PTS": 81}}]}