{"1": [{"Richmond": {"KI": 207, "MK": 68, "HB": 133, "DI": 340, "GL": 17, "BH": 19, "HO": 34, "TK": 70, "RB": 29, "IF": 71, "CL": 41, "CG": 56, "FF": 22, "FA": 20, "PTS": 121}, "Carlton": {"KI": 207, "MK": 88, "HB": 169, "DI": 376, "GL": 15, "BH": 5, "HO": 42, "TK": 49, "RB": 47, "IF": 47, "CL": 42, "CG": 57, "FF": 20, "FA": 22, "PTS": 95}}, {"Essendon": {"KI": 214, "MK": 92, "HB": 177, "DI": 391, "GL": 14, "BH": 15, "HO": 39, "TK": 69, "RB": 39, "IF": 60, "CL": 32, "CG": 48, "FF": 19, "FA": 12, "PTS": 99}, "Adelaide": {"KI": 204, "MK": 83, "HB": 183, "DI": 387, "GL": 12, "BH": 15, "HO": 37, "TK": 50, "RB": 43, "IF": 53, "CL": 40, "CG": 48, "FF": 12, "FA": 19, "PTS": 87}}, {"St Kilda": {"KI": 242, "MK": 135, "HB": 180, "DI": 422, "GL": 16, "BH": 11, "HO": 25, "TK": 48, "RB": 35, "IF": 59, "CL": 27, "CG": 57, "FF": 21, "FA": 25, "PTS": 107}, "Brisbane Lions": {"KI": 215, "MK": 87, "HB": 160, "DI": 375, "GL": 12, "BH": 10, "HO": 44, "TK": 44, "RB": 37, "IF": 49, "CL": 44, "CG": 65, "FF": 25, "FA": 21, "PTS": 82}}, {"Port Adelaide": {"KI": 260, "MK": 112, "HB": 179, "DI": 439, "GL": 16, "BH": 14, "HO": 26, "TK": 63, "RB": 38, "IF": 62, "CL": 45, "CG": 51, "FF": 23, "FA": 17, "PTS": 110}, "Fremantle": {"KI": 198, "MK": 95, "HB": 160, "DI": 358, "GL": 9, "BH": 6, "HO": 57, "TK": 44, "RB": 43, "IF": 49, "CL": 35, "CG": 52, "FF": 17, "FA": 23, "PTS": 60}}, {"Gold Coast": {"KI": 295, "MK": 59, "HB": 109, "DI": 404, "GL": 7, "BH": 13, "HO": 42, "TK": 100, "RB": 40, "IF": 67, "CL": 54, "CG": 89, "FF": 22, "FA": 24, "PTS": 55}, "North Melbourne": {"KI": 217, "MK": 21, "HB": 130, "DI": 347, "GL": 5, "BH": 9, "HO": 46, "TK": 88, "RB": 54, "IF": 47, "CL": 37, "CG": 81, "FF": 24, "FA": 22, "PTS": 39}}, {"Hawthorn": {"KI": 225, "MK": 86, "HB": 177, "DI": 402, "GL": 15, "BH": 11, "HO": 29, "TK": 64, "RB": 41, "IF": 60, "CL": 33, "CG": 75, "FF": 20, "FA": 30, "PTS": 101}, "Collingwood": {"KI": 205, "MK": 70, "HB": 158, "DI": 363, "GL": 9, "BH": 13, "HO": 46, "TK": 71, "RB": 37, "IF": 58, "CL": 40, "CG": 64, "FF": 30, "FA": 20, "PTS": 67}}, {"Greater Western Sydney": {"KI": 246, "MK": 119, "HB": 191, "DI": 437, "GL": 20, "BH": 13, "HO": 43, "TK": 62, "RB": 39, "IF": 69, "CL": 38, "CG": 60, "FF": 15, "FA": 23, "PTS": 133}, "Western Bulldogs": {"KI": 196, "MK": 68, "HB": 151, "DI": 347, "GL": 7, "BH": 9, "HO": 46, "TK": 57, "RB": 43, "IF": 51, "CL": 44, "CG": 57, "FF": 23, "FA": 15, "PTS": 51}}, {"Melbourne": {"KI": 185, "MK": 52, "HB": 173, "DI": 358, "GL": 13, "BH": 16, "HO": 51, "TK": 72, "RB": 20, "IF": 64, "CL": 44, "CG": 58, "FF": 26, "FA": 17, "PTS": 94}, "Geelong": {"KI": 220, "MK": 103, "HB": 198, "DI": 418, "GL": 14, "BH": 13, "HO": 30, "TK": 45, "RB": 45, "IF": 41, "CL": 36, "CG": 59, "FF": 17, "FA": 26, "PTS": 97}}, {"West Coast": {"KI": 226, "MK": 84, "HB": 113, "DI": 339, "GL": 13, "BH": 8, "HO": 66, "TK": 64, "RB": 32, "IF": 60, "CL": 38, "CG": 60, "FF": 20, "FA": 28, "PTS": 86}, "Sydney": {"KI": 219, "MK": 82, "HB": 174, "DI": 393, "GL": 18, "BH": 7, "HO": 17, "TK": 62, "RB": 46, "IF": 52, "CL": 47, "CG": 52, "FF": 28, "FA": 21, "PTS": 115}}], "2": [{"Adelaide": {"KI": 261, "MK": 106, "HB": 188, "DI": 449, "GL": 18, "BH": 10, "HO": 48, "TK": 48, "RB": 35, "IF": 64, "CL": 40, "CG": 60, "FF": 28, "FA": 14, "PTS": 118}, "Richmond": {"KI": 183, "MK": 52, "HB": 126, "DI": 309, "GL": 12, "BH": 10, "HO": 26, "TK": 71, "RB": 43, "IF": 49, "CL": 37, "CG": 68, "FF": 14, "FA": 28, "PTS": 82}}, {"North Melbourne": {"KI": 222, "MK": 100, "HB": 142, "DI": 364, "GL": 13, "BH": 17, "HO": 51, "TK": 65, "RB": 31, "IF": 66, "CL": 30, "CG": 56, "FF": 23, "FA": 16, "PTS": 95}, "St Kilda": {"KI": 192, "MK": 87, "HB": 180, "DI": 372, "GL": 5, "BH": 13, "HO": 19, "TK": 75, "RB": 49, "IF": 41, "CL": 28, "CG": 66, "FF": 16, "FA": 23, "PTS": 43}}, {"Carlton": {"KI": 231, "MK": 86, "HB": 156, "DI": 387, "GL": 9, "BH": 13, "HO": 19, "TK": 67, "RB": 33, "IF": 67, "CL": 37, "CG": 64, "FF": 26, "FA": 24, "PTS": 67}, "Gold Coast": {"KI": 221, "MK": 77, "HB": 129, "DI": 350, "GL": 15, "BH": 11, "HO": 58, "TK": 93, "RB": 55, "IF": 50, "CL": 46, "CG": 68, "FF": 24, "FA": 26, "PTS": 101}}, {"Collingwood": {"KI": 211, "MK": 85, "HB": 196, "DI": 407, "GL": 12, "BH": 7, "HO": 48, "TK": 72, "RB": 34, "IF": 53, "CL": 37, "CG": 67, "FF": 28, "FA": 20, "PTS": 79}, "Greater Western Sydney": {"KI": 223, "MK": 96, "HB": 159, "DI": 382, "GL": 15, "BH": 5, "HO": 22, "TK": 63, "RB": 41, "IF": 51, "CL": 41, "CG": 76, "FF": 20, "FA": 28, "PTS": 95}}, {"Brisbane Lions": {"KI": 190, "MK": 59, "HB": 149, "DI": 339, "GL": 10, "BH": 14, "HO": 39, "TK": 83, "RB": 37, "IF": 52, "CL": 45, "CG": 45, "FF": 24, "FA": 15, "PTS": 74}, "Melbourne": {"KI": 209, "MK": 76, "HB": 160, "DI": 369, "GL": 14, "BH": 16, "HO": 54, "TK": 75, "RB": 38, "IF": 56, "CL": 45, "CG": 51, "FF": 15, "FA": 24, "PTS": 100}}, {"Fremantle": {"KI": 241, "MK": 105, "HB": 158, "DI": 399, "GL": 16, "BH": 10, "HO": 42, "TK": 65, "RB": 28, "IF": 56, "CL": 32, "CG": 63, "FF": 23, "FA": 22, "PTS": 106}, "Essendon": {"KI": 192, "MK": 71, "HB": 167, "DI": 359, "GL": 14, "BH": 6, "HO": 18, "TK": 72, "RB": 38, "IF": 45, "CL": 30, "CG": 61, "FF": 22, "FA": 23, "PTS": 90}}, {"Western Bulldogs": {"KI": 219, "MK": 115, "HB": 134, "DI": 353, "GL": 9, "BH": 16, "HO": 13, "TK": 42, "RB": 35, "IF": 54, "CL": 33, "CG": 45, "FF": 19, "FA": 18, "PTS": 70}, "West Coast": {"KI": 245, "MK": 124, "HB": 115, "DI": 360, "GL": 18, "BH": 13, "HO": 54, "TK": 49, "RB": 43, "IF": 58, "CL": 32, "CG": 49, "FF": 18, "FA": 19, "PTS": 121}}, {"Sydney": {"KI": 217, "MK": 65, "HB": 163, "DI": 380, "GL": 10, "BH": 11, "HO": 51, "TK": 71, "RB": 35, "IF": 52, "CL": 52, "CG": 69, "FF": 17, "FA": 20, "PTS": 71}, "Port Adelaide": {"KI": 226, "MK": 69, "HB": 141, "DI": 367, "GL": 14, "BH": 10, "HO": 44, "TK": 80, "RB": 40, "IF": 52, "CL": 46, "CG": 53, "FF": 20, "FA": 17, "PTS": 94}}, {"Geelong": {"KI": 213, "MK": 102, "HB": 159, "DI": 372, "GL": 18, "BH": 9, "HO": 35, "TK": 51, "RB": 38, "IF": 43, "CL": 41, "CG": 44, "FF": 27, "FA": 19, "PTS": 117}, "Hawthorn": {"KI": 201, "MK": 88, "HB": 122, "DI": 323, "GL": 17, "BH": 16, "HO": 50, "TK": 62, "RB": 22, "IF": 62, "CL": 47, "CG": 50, "FF": 19, "FA": 27, "PTS": 118}}], "3": [{"Carlton": {"KI": 208, "MK": 84, "HB": 128, "DI": 336, "GL": 11, "BH": 10, "HO": 36, "TK": 55, "RB": 34, "IF": 55, "CL": 36, "CG": 59, "FF": 23, "FA": 28, "PTS": 76}, "Collingwood": {"KI": 227, "MK": 113, "HB": 190, "DI": 417, "GL": 16, "BH": 4, "HO": 37, "TK": 69, "RB": 41, "IF": 50, "CL": 33, "CG": 54, "FF": 28, "FA": 23, "PTS": 100}}, {"Port Adelaide": {"KI": 235, "MK": 111, "HB": 149, "DI": 384, "GL": 14, "BH": 13, "HO": 22, "TK": 45, "RB": 28, "IF": 55, "CL": 33, "CG": 60, "FF": 20, "FA": 27, "PTS": 97}, "Brisbane Lions": {"KI": 203, "MK": 87, "HB": 129, "DI": 332, "GL": 14, "BH": 8, "HO": 55, "TK": 61, "RB": 36, "IF": 43, "CL": 41, "CG": 53, "FF": 27, "FA": 20, "PTS": 92}}, {"Melbourne": {"KI": 231, "MK": 94, "HB": 168, "DI": 399, "GL": 18, "BH": 15, "HO": 52, "TK": 59, "RB": 27, "IF": 66, "CL": 37, "CG": 58, "FF": 25, "FA": 23, "PTS": 123}, "North Melbourne": {"KI": 176, "MK": 74, "HB": 138, "DI": 314, "GL": 13, "BH": 8, "HO": 24, "TK": 62, "RB": 41, "IF": 45, "CL": 36, "CG": 63, "FF": 23, "FA": 25, "PTS": 86}}, {"Gold Coast": {"KI": 220, "MK": 95, "HB": 104, "DI": 324, "GL": 10, "BH": 8, "HO": 29, "TK": 59, "RB": 39, "IF": 46, "CL": 29, "CG": 72, "FF": 22, "FA": 21, "PTS": 68}, "Fremantle": {"KI": 232, "MK": 105, "HB": 155, "DI": 387, "GL": 13, "BH": 18, "HO": 38, "TK": 53, "RB": 34, "IF": 59, "CL": 37, "CG": 55, "FF": 21, "FA": 22, "PTS": 96}}, {"St Kilda": {"KI": 220, "MK": 101, "HB": 157, "DI": 377, "GL": 7, "BH": 13, "HO": 22, "TK": 51, "RB": 31, "IF": 54, "CL": 31, "CG": 53, "FF": 17, "FA": 21, "PTS": 55}, "Adelaide": {"KI": 236, "MK": 111, "HB": 161, "DI": 397, "GL": 15, "BH": 14, "HO": 42, "TK": 79, "RB": 41, "IF": 51, "CL": 34, "CG": 42, "FF": 21, "FA": 17, "PTS": 104}}, {"Sydney": {"KI": 223, "MK": 98, "HB": 139, "DI": 362, "GL": 16, "BH": 7, "HO": 50, "TK": 51, "RB": 39, "IF": 50, "CL": 33, "CG": 54, "FF": 26, "FA": 18, "PTS": 103}, "Greater Western Sydney": {"KI": 214, "MK": 91, "HB": 146, "DI": 360, "GL": 12, "BH": 15, "HO": 26, "TK": 76, "RB": 34, "IF": 54, "CL": 47, "CG": 56, "FF": 18, "FA": 26, "PTS": 87}}, {"Richmond": {"KI": 215, "MK": 102, "HB": 176, "DI": 391, "GL": 15, "BH": 12, "HO": 30, "TK": 50, "RB": 35, "IF": 55, "CL": 31, "CG": 46, "FF": 16, "FA": 24, "PTS": 102}, "Hawthorn": {"KI": 219, "MK": 91, "HB": 144, "DI": 363, "GL": 13, "BH": 11, "HO": 42, "TK": 53, "RB": 34, "IF": 51, "CL": 39, "CG": 57, "FF": 24, "FA": 16, "PTS": 89}}, {"Western Bulldogs": {"KI": 254, "MK": 152, "HB": 163, "DI": 417, "GL": 14, "BH": 20, "HO": 22, "TK": 44, "RB": 30, "IF": 56, "CL": 30, "CG": 50, "FF": 19, "FA": 21, "PTS": 104}, "Essendon": {"KI": 186, "MK": 80, "HB": 137, "DI": 323, "GL": 12, "BH": 11, "HO": 38, "TK": 43, "RB": 38, "IF": 44, "CL": 27, "CG": 67, "FF": 21, "FA": 19, "PTS": 83}}, {"West Coast": {"KI": 227, "MK": 95, "HB": 115, "DI": 342, "GL": 14, "BH": 11, "HO": 56, "TK": 53, "RB": 39, "IF": 60, "CL": 40, "CG": 52, "FF": 26, "FA": 19, "PTS": 95}, "Geelong": {"KI": 224, "MK": 105, "HB": 159, "DI": 383, "GL": 11, "BH": 14, "HO": 27, "TK": 62, "RB": 42, "IF": 55, "CL": 39, "CG": 58, "FF": 18, "FA": 26, "PTS": 80}}], "4": [{"Adelaide": {"KI": 211, "MK": 80, "HB": 161, "DI": 372, "GL": 9, "BH": 4, "HO": 37, "TK": 67, "RB": 41, "IF": 49, "CL": 34, "CG": 64, "FF": 20, "FA": 19, "PTS": 58}, "Collingwood": {"KI": 215, "MK": 52, "HB": 217, "DI": 432, "GL": 16, "BH": 10, "HO": 50, "TK": 77, "RB": 39, "IF": 58, "CL": 57, "CG": 75, "FF": 19, "FA": 20, "PTS": 106}}, {"Greater Western Sydney": {"KI": 239, "MK": 115, "HB": 186, "DI": 425, "GL": 11, "BH": 16, "HO": 32, "TK": 60, "RB": 45, "IF": 53, "CL": 28, "CG": 52, "FF": 20, "FA": 14, "PTS": 82}, "Fremantle": {"KI": 200, "MK": 89, "HB": 162, "DI": 362, "GL": 7, "BH": 9, "HO": 48, "TK": 56, "RB": 40, "IF": 56, "CL": 40, "CG": 51, "FF": 14, "FA": 20, "PTS": 51}}, {"Richmond": {"KI": 201, "MK": 80, "HB": 196, "DI": 397, "GL": 16, "BH": 14, "HO": 17, "TK": 57, "RB": 34, "IF": 53, "CL": 25, "CG": 54, "FF": 27, "FA": 26, "PTS": 110}, "Brisbane Lions": {"KI": 210, "MK": 94, "HB": 176, "DI": 386, "GL": 2, "BH": 5, "HO": 25, "TK": 42, "RB": 34, "IF": 39, "CL": 28, "CG": 62, "FF": 26, "FA": 27, "PTS": 17}}, {"Western Bulldogs": {"KI": 235, "MK": 113, "HB": 162, "DI": 397, "GL": 11, "BH": 13, "HO": 28, "TK": 56, "RB": 26, "IF": 60, "CL": 35, "CG": 46, "FF": 29, "FA": 16, "PTS": 79}, "Sydney": {"KI": 182, "MK": 85, "HB": 163, "DI": 345, "GL": 13, "BH": 8, "HO": 43, "TK": 47, "RB": 48, "IF": 42, "CL": 27, "CG": 60, "FF": 16, "FA": 29, "PTS": 86}}, {"North Melbourne": {"KI": 238, "MK": 97, "HB": 147, "DI": 385, "GL": 18, "BH": 8, "HO": 41, "TK": 66, "RB": 34, "IF": 56, "CL": 37, "CG": 57, "FF": 22, "FA": 22, "PTS": 116}, "Carlton": {"KI": 192, "MK": 78, "HB": 106, "DI": 298, "GL": 4, "BH": 6, "HO": 33, "TK": 65, "RB": 36, "IF": 42, "CL": 38, "CG": 66, "FF": 22, "FA": 22, "PTS": 30}}, {"West Coast": {"KI": 256, "MK": 127, "HB": 148, "DI": 404, "GL": 21, "BH": 13, "HO": 45, "TK": 47, "RB": 36, "IF": 57, "CL": 31, "CG": 49, "FF": 28, "FA": 19, "PTS": 139}, "Gold Coast": {"KI": 209, "MK": 89, "HB": 123, "DI": 332, "GL": 9, "BH": 5, "HO": 18, "TK": 45, "RB": 33, "IF": 46, "CL": 32, "CG": 71, "FF": 19, "FA": 28, "PTS": 59}}, {"Essendon": {"KI": 227, "MK": 96, "HB": 160, "DI": 387, "GL": 16, "BH": 10, "HO": 46, "TK": 64, "RB": 32, "IF": 57, "CL": 45, "CG": 49, "FF": 15, "FA": 21, "PTS": 106}, "Port Adelaide": {"KI": 184, "MK": 69, "HB": 181, "DI": 365, "GL": 12, "BH": 12, "HO": 39, "TK": 61, "RB": 38, "IF": 47, "CL": 41, "CG": 54, "FF": 21, "FA": 15, "PTS": 84}}, {"Hawthorn": {"KI": 223, "MK": 58, "HB": 140, "DI": 363, "GL": 18, "BH": 7, "HO": 34, "TK": 113, "RB": 39, "IF": 54, "CL": 56, "CG": 71, "FF": 27, "FA": 24, "PTS": 115}, "Melbourne": {"KI": 196, "MK": 50, "HB": 156, "DI": 352, "GL": 6, "BH": 12, "HO": 72, "TK": 74, "RB": 32, "IF": 53, "CL": 38, "CG": 77, "FF": 24, "FA": 27, "PTS": 48}}, {"Geelong": {"KI": 222, "MK": 87, "HB": 138, "DI": 360, "GL": 15, "BH": 13, "HO": 39, "TK": 71, "RB": 28, "IF": 62, "CL": 29, "CG": 62, "FF": 25, "FA": 23, "PTS": 103}, "St Kilda": {"KI": 219, "MK": 68, "HB": 163, "DI": 382, "GL": 7, "BH": 14, "HO": 31, "TK": 61, "RB": 41, "IF": 44, "CL": 44, "CG": 71, "FF": 23, "FA": 25, "PTS": 56}}], "5": [{"Sydney": {"KI": 221, "MK": 91, "HB": 154, "DI": 375, "GL": 10, "BH": 15, "HO": 37, "TK": 64, "RB": 35, "IF": 64, "CL": 35, "CG": 56, "FF": 18, "FA": 19, "PTS": 75}, "Adelaide": {"KI": 230, "MK": 91, "HB": 141, "DI": 371, "GL": 12, "BH": 13, "HO": 48, "TK": 60, "RB": 47, "IF": 48, "CL": 39, "CG": 51, "FF": 19, "FA": 18, "PTS": 85}}, {"St Kilda": {"KI": 207, "MK": 82, "HB": 163, "DI": 370, "GL": 10, "BH": 13, "HO": 31, "TK": 79, "RB": 35, "IF": 67, "CL": 30, "CG": 42, "FF": 18, "FA": 20, "PTS": 73}, "Greater Western Sydney": {"KI": 208, "MK": 84, "HB": 166, "DI": 374, "GL": 9, "BH": 19, "HO": 43, "TK": 63, "RB": 52, "IF": 47, "CL": 36, "CG": 44, "FF": 20, "FA": 18, "PTS": 73}}, {"Carlton": {"KI": 219, "MK": 104, "HB": 122, "DI": 341, "GL": 10, "BH": 9, "HO": 30, "TK": 70, "RB": 36, "IF": 47, "CL": 35, "CG": 58, "FF": 25, "FA": 16, "PTS": 69}, "West Coast": {"KI": 208, "MK": 88, "HB": 126, "DI": 334, "GL": 10, "BH": 19, "HO": 49, "TK": 63, "RB": 37, "IF": 53, "CL": 35, "CG": 61, "FF": 16, "FA": 25, "PTS": 79}}, {"Port Adelaide": {"KI": 240, "MK": 111, "HB": 149, "DI": 389, "GL": 7, "BH": 8, "HO": 42, "TK": 79, "RB": 38, "IF": 52, "CL": 49, "CG": 64, "FF": 20, "FA": 24, "PTS": 50}, "Geelong": {"KI": 196, "MK": 66, "HB": 151, "DI": 347, "GL": 12, "BH": 12, "HO": 64, "TK": 81, "RB": 40, "IF": 53, "CL": 44, "CG": 61, "FF": 24, "FA": 20, "PTS": 84}}, {"Fremantle": {"KI": 224, "MK": 110, "HB": 183, "DI": 407, "GL": 16, "BH": 12, "HO": 61, "TK": 54, "RB": 33, "IF": 59, "CL": 37, "CG": 69, "FF": 15, "FA": 25, "PTS": 108}, "Western Bulldogs": {"KI": 215, "MK": 108, "HB": 152, "DI": 367, "GL": 8, "BH": 6, "HO": 18, "TK": 63, "RB": 37, "IF": 42, "CL": 32, "CG": 57, "FF": 25, "FA": 15, "PTS": 54}}, {"North Melbourne": {"KI": 229, "MK": 101, "HB": 144, "DI": 373, "GL": 14, "BH": 14, "HO": 35, "TK": 66, "RB": 38, "IF": 48, "CL": 37, "CG": 59, "FF": 24, "FA": 17, "PTS": 98}, "Hawthorn": {"KI": 211, "MK": 99, "HB": 147, "DI": 358, "GL": 11, "BH": 4, "HO": 34, "TK": 47, "RB": 27, "IF": 52, "CL": 25, "CG": 68, "FF": 17, "FA": 24, "PTS": 70}}, {"Brisbane Lions": {"KI": 227, "MK": 108, "HB": 173, "DI": 400, "GL": 10, "BH": 11, "HO": 30, "TK": 58, "RB": 40, "IF": 60, "CL": 33, "CG": 65, "FF": 23, "FA": 23, "PTS": 71}, "Gold Coast": {"KI": 227, "MK": 91, "HB": 141, "DI": 368, "GL": 11, "BH": 10, "HO": 34, "TK": 54, "RB": 48, "IF": 55, "CL": 35, "CG": 58, "FF": 23, "FA": 23, "PTS": 76}}, {"Melbourne": {"KI": 195, "MK": 77, "HB": 163, "DI": 358, "GL": 8, "BH": 8, "HO": 65, "TK": 79, "RB": 38, "IF": 46, "CL": 36, "CG": 67, "FF": 22, "FA": 20, "PTS": 56}, "Richmond": {"KI": 212, "MK": 61, "HB": 162, "DI": 374, "GL": 15, "BH": 12, "HO": 23, "TK": 78, "RB": 37, "IF": 59, "CL": 42, "CG": 57, "FF": 20, "FA": 22, "PTS": 102}}, {"Collingwood": {"KI": 206, "MK": 90, "HB": 201, "DI": 407, "GL": 14, "BH": 17, "HO": 37, "TK": 48, "RB": 31, "IF": 58, "CL": 25, "CG": 40, "FF": 20, "FA": 13, "PTS": 101}, "Essendon": {"KI": 225, "MK": 127, "HB": 188, "DI": 413, "GL": 7, "BH": 10, "HO": 23, "TK": 48, "RB": 39, "IF": 41, "CL": 34, "CG": 51, "FF": 13, "FA": 20, "PTS": 52}}], "6": [{"Western Bulldogs": {"KI": 187, "MK": 90, "HB": 208, "DI": 395, "GL": 11, "BH": 14, "HO": 22, "TK": 74, "RB": 35, "IF": 49, "CL": 31, "CG": 41, "FF": 22, "FA": 19, "PTS": 80}, "Carlton": {"KI": 189, "MK": 78, "HB": 150, "DI": 339, "GL": 8, "BH": 11, "HO": 54, "TK": 68, "RB": 29, "IF": 45, "CL": 30, "CG": 53, "FF": 19, "FA": 22, "PTS": 59}}, {"Geelong": {"KI": 186, "MK": 63, "HB": 133, "DI": 319, "GL": 10, "BH": 9, "HO": 50, "TK": 74, "RB": 33, "IF": 52, "CL": 34, "CG": 48, "FF": 25, "FA": 17, "PTS": 69}, "Sydney": {"KI": 219, "MK": 96, "HB": 150, "DI": 369, "GL": 12, "BH": 14, "HO": 42, "TK": 85, "RB": 42, "IF": 52, "CL": 50, "CG": 49, "FF": 17, "FA": 25, "PTS": 86}}, {"North Melbourne": {"KI": 172, "MK": 61, "HB": 173, "DI": 345, "GL": 10, "BH": 9, "HO": 44, "TK": 63, "RB": 27, "IF": 47, "CL": 32, "CG": 58, "FF": 21, "FA": 21, "PTS": 69}, "Port Adelaide": {"KI": 217, "MK": 89, "HB": 186, "DI": 403, "GL": 15, "BH": 12, "HO": 29, "TK": 81, "RB": 36, "IF": 51, "CL": 38, "CG": 55, "FF": 21, "FA": 21, "PTS": 102}}, {"Greater Western Sydney": {"KI": 235, "MK": 120, "HB": 189, "DI": 424, "GL": 10, "BH": 17, "HO": 4, "TK": 56, "RB": 34, "IF": 46, "CL": 31, "CG": 64, "FF": 21, "FA": 24, "PTS": 77}, "Brisbane Lions": {"KI": 203, "MK": 96, "HB": 154, "DI": 357, "GL": 5, "BH": 13, "HO": 47, "TK": 51, "RB": 31, "IF": 43, "CL": 28, "CG": 61, "FF": 24, "FA": 21, "PTS": 43}}, {"Hawthorn": {"KI": 236, "MK": 102, "HB": 181, "DI": 417, "GL": 13, "BH": 11, "HO": 33, "TK": 59, "RB": 27, "IF": 56, "CL": 28, "CG": 46, "FF": 18, "FA": 14, "PTS": 89}, "St Kilda": {"KI": 199, "MK": 85, "HB": 160, "DI": 359, "GL": 7, "BH": 12, "HO": 22, "TK": 64, "RB": 40, "IF": 42, "CL": 27, "CG": 52, "FF": 14, "FA": 18, "PTS": 54}}, {"Adelaide": {"KI": 252, "MK": 113, "HB": 205, "DI": 457, "GL": 16, "BH": 14, "HO": 36, "TK": 58, "RB": 29, "IF": 54, "CL": 30, "CG": 51, "FF": 29, "FA": 14, "PTS": 110}, "Gold Coast": {"KI": 196, "MK": 82, "HB": 153, "DI": 349, "GL": 9, "BH": 8, "HO": 36, "TK": 84, "RB": 35, "IF": 40, "CL": 42, "CG": 58, "FF": 14, "FA": 29, "PTS": 62}}, {"Essendon": {"KI": 204, "MK": 81, "HB": 197, "DI": 401, "GL": 10, "BH": 12, "HO": 26, "TK": 78, "RB": 34, "IF": 47, "CL": 28, "CG": 57, "FF": 21, "FA": 23, "PTS": 72}, "Melbourne": {"KI": 196, "MK": 94, "HB": 163, "DI": 359, "GL": 16, "BH": 12, "HO": 45, "TK": 69, "RB": 34, "IF": 55, "CL": 38, "CG": 49, "FF": 23, "FA": 21, "PTS": 108}}, {"Collingwood": {"KI": 209, "MK": 105, "HB": 223, "DI": 432, "GL": 10, "BH": 10, "HO": 44, "TK": 69, "RB": 47, "IF": 51, "CL": 24, "CG": 63, "FF": 27, "FA": 16, "PTS": 70}, "Richmond": {"KI": 202, "MK": 75, "HB": 178, "DI": 380, "GL": 16, "BH": 17, "HO": 17, "TK": 47, "RB": 36, "IF": 67, "CL": 36, "CG": 83, "FF": 16, "FA": 27, "PTS": 113}}, {"Fremantle": {"KI": 189, "MK": 92, "HB": 167, "DI": 356, "GL": 12, "BH": 9, "HO": 35, "TK": 67, "RB": 37, "IF": 45, "CL": 31, "CG": 55, "FF": 20, "FA": 22, "PTS": 81}, "West Coast": {"KI": 235, "MK": 105, "HB": 136, "DI": 371, "GL": 13, "BH": 11, "HO": 52, "TK": 63, "RB": 30, "IF": 55, "CL": 44, "CG": 48, "FF": 22, "FA": 20, "PTS": 89}}], "7": [{"Geelong": {"KI": 251, "MK": 127, "HB": 165, "DI": 416, "GL": 14, "BH": 9, "HO": 45, "TK": 66, "RB": 37, "IF": 62, "CL": 40, "CG": 56, "FF": 20, "FA": 17, "PTS": 93}, "Greater Western Sydney": {"KI": 191, "MK": 60, "HB": 141, "DI": 332, "GL": 4, "BH": 8, "HO": 31, "TK": 74, "RB": 48, "IF": 44, "CL": 37, "CG": 71, "FF": 17, "FA": 20, "PTS": 32}}, {"Western Bulldogs": {"KI": 212, "MK": 75, "HB": 201, "DI": 413, "GL": 11, "BH": 15, "HO": 19, "TK": 80, "RB": 44, "IF": 61, "CL": 52, "CG": 56, "FF": 15, "FA": 24, "PTS": 81}, "Gold Coast": {"KI": 196, "MK": 60, "HB": 182, "DI": 378, "GL": 10, "BH": 12, "HO": 65, "TK": 91, "RB": 44, "IF": 59, "CL": 31, "CG": 44, "FF": 24, "FA": 15, "PTS": 72}}, {"Essendon": {"KI": 185, "MK": 84, "HB": 205, "DI": 390, "GL": 10, "BH": 7, "HO": 35, "TK": 45, "RB": 35, "IF": 39, "CL": 33, "CG": 61, "FF": 17, "FA": 22, "PTS": 67}, "Hawthorn": {"KI": 205, "MK": 92, "HB": 141, "DI": 346, "GL": 13, "BH": 12, "HO": 35, "TK": 72, "RB": 25, "IF": 54, "CL": 34, "CG": 41, "FF": 22, "FA": 17, "PTS": 90}}, {"West Coast": {"KI": 230, "MK": 85, "HB": 145, "DI": 375, "GL": 16, "BH": 6, "HO": 56, "TK": 54, "RB": 32, "IF": 52, "CL": 45, "CG": 46, "FF": 30, "FA": 13, "PTS": 102}, "Port Adelaide": {"KI": 187, "MK": 87, "HB": 193, "DI": 380, "GL": 9, "BH": 6, "HO": 26, "TK": 66, "RB": 32, "IF": 45, "CL": 31, "CG": 63, "FF": 13, "FA": 30, "PTS": 60}}, {"Sydney": {"KI": 203, "MK": 84, "HB": 146, "DI": 349, "GL": 9, "BH": 12, "HO": 27, "TK": 59, "RB": 36, "IF": 58, "CL": 41, "CG": 51, "FF": 16, "FA": 23, "PTS": 66}, "North Melbourne": {"KI": 218, "MK": 101, "HB": 153, "DI": 371, "GL": 9, "BH": 14, "HO": 48, "TK": 48, "RB": 39, "IF": 48, "CL": 31, "CG": 53, "FF": 23, "FA": 16, "PTS": 68}}, {"Adelaide": {"KI": 216, "MK": 95, "HB": 170, "DI": 386, "GL": 19, "BH": 11, "HO": 38, "TK": 60, "RB": 27, "IF": 54, "CL": 36, "CG": 43, "FF": 18, "FA": 10, "PTS": 125}, "Carlton": {"KI": 220, "MK": 107, "HB": 112, "DI": 332, "GL": 10, "BH": 10, "HO": 41, "TK": 66, "RB": 33, "IF": 37, "CL": 36, "CG": 58, "FF": 11, "FA": 18, "PTS": 70}}, {"Richmond": {"KI": 222, "MK": 106, "HB": 181, "DI": 403, "GL": 15, "BH": 20, "HO": 16, "TK": 69, "RB": 36, "IF": 64, "CL": 23, "CG": 58, "FF": 19, "FA": 24, "PTS": 110}, "Fremantle": {"KI": 180, "MK": 73, "HB": 166, "DI": 346, "GL": 4, "BH": 9, "HO": 57, "TK": 41, "RB": 37, "IF": 42, "CL": 43, "CG": 62, "FF": 24, "FA": 19, "PTS": 33}}, {"St Kilda": {"KI": 191, "MK": 88, "HB": 240, "DI": 431, "GL": 9, "BH": 13, "HO": 30, "TK": 63, "RB": 42, "IF": 56, "CL": 31, "CG": 54, "FF": 15, "FA": 20, "PTS": 67}, "Melbourne": {"KI": 219, "MK": 103, "HB": 202, "DI": 421, "GL": 16, "BH": 10, "HO": 34, "TK": 52, "RB": 44, "IF": 63, "CL": 37, "CG": 61, "FF": 20, "FA": 15, "PTS": 106}}, {"Brisbane Lions": {"KI": 221, "MK": 109, "HB": 152, "DI": 373, "GL": 18, "BH": 6, "HO": 34, "TK": 56, "RB": 40, "IF": 56, "CL": 37, "CG": 58, "FF": 21, "FA": 18, "PTS": 114}, "Collingwood": {"KI": 223, "MK": 99, "HB": 163, "DI": 386, "GL": 19, "BH": 7, "HO": 49, "TK": 56, "RB": 37, "IF": 61, "CL": 49, "CG": 57, "FF": 18, "FA": 21, "PTS": 121}}], "8": [{"Hawthorn": {"KI": 233, "MK": 93, "HB": 147, "DI": 380, "GL": 10, "BH": 11, "HO": 42, "TK": 84, "RB": 24, "IF": 63, "CL": 28, "CG": 61, "FF": 21, "FA": 21, "PTS": 71}, "Sydney": {"KI": 218, "MK": 77, "HB": 214, "DI": 432, "GL": 12, "BH": 7, "HO": 41, "TK": 74, "RB": 50, "IF": 39, "CL": 40, "CG": 64, "FF": 21, "FA": 21, "PTS": 79}}, {"Greater Western Sydney": {"KI": 194, "MK": 61, "HB": 166, "DI": 360, "GL": 8, "BH": 13, "HO": 59, "TK": 75, "RB": 40, "IF": 53, "CL": 45, "CG": 60, "FF": 16, "FA": 20, "PTS": 61}, "West Coast": {"KI": 228, "MK": 91, "HB": 144, "DI": 372, "GL": 12, "BH": 14, "HO": 36, "TK": 74, "RB": 40, "IF": 55, "CL": 40, "CG": 49, "FF": 20, "FA": 16, "PTS": 86}}, {"Carlton": {"KI": 219, "MK": 92, "HB": 110, "DI": 329, "GL": 14, "BH": 7, "HO": 34, "TK": 91, "RB": 34, "IF": 50, "CL": 45, "CG": 36, "FF": 26, "FA": 16, "PTS": 91}, "Essendon": {"KI": 201, "MK": 74, "HB": 143, "DI": 344, "GL": 10, "BH": 18, "HO": 63, "TK": 91, "RB": 35, "IF": 54, "CL": 40, "CG": 54, "FF": 16, "FA": 26, "PTS": 78}}, {"Gold Coast": {"KI": 197, "MK": 79, "HB": 132, "DI": 329, "GL": 11, "BH": 11, "HO": 38, "TK": 55, "RB": 55, "IF": 43, "CL": 32, "CG": 62, "FF": 21, "FA": 23, "PTS": 77}, "Melbourne": {"KI": 227, "MK": 91, "HB": 199, "DI": 426, "GL": 21, "BH": 20, "HO": 47, "TK": 65, "RB": 24, "IF": 83, "CL": 49, "CG": 49, "FF": 23, "FA": 21, "PTS": 146}}, {"Port Adelaide": {"KI": 233, "MK": 101, "HB": 178, "DI": 411, "GL": 14, "BH": 11, "HO": 48, "TK": 81, "RB": 37, "IF": 49, "CL": 43, "CG": 51, "FF": 24, "FA": 14, "PTS": 95}, "Adelaide": {"KI": 221, "MK": 102, "HB": 115, "DI": 336, "GL": 14, "BH": 6, "HO": 35, "TK": 56, "RB": 33, "IF": 50, "CL": 36, "CG": 60, "FF": 14, "FA": 24, "PTS": 90}}, {"Western Bulldogs": {"KI": 208, "MK": 74, "HB": 231, "DI": 439, "GL": 16, "BH": 11, "HO": 20, "TK": 67, "RB": 31, "IF": 64, "CL": 43, "CG": 45, "FF": 21, "FA": 15, "PTS": 107}, "Brisbane Lions": {"KI": 205, "MK": 86, "HB": 130, "DI": 335, "GL": 14, "BH": 9, "HO": 63, "TK": 86, "RB": 45, "IF": 47, "CL": 35, "CG": 53, "FF": 15, "FA": 21, "PTS": 93}}, {"Fremantle": {"KI": 215, "MK": 104, "HB": 189, "DI": 404, "GL": 13, "BH": 11, "HO": 44, "TK": 53, "RB": 34, "IF": 57, "CL": 39, "CG": 51, "FF": 16, "FA": 23, "PTS": 89}, "St Kilda": {"KI": 189, "MK": 84, "HB": 184, "DI": 373, "GL": 8, "BH": 11, "HO": 24, "TK": 63, "RB": 37, "IF": 46, "CL": 29, "CG": 50, "FF": 23, "FA": 16, "PTS": 59}}, {"North Melbourne": {"KI": 194, "MK": 79, "HB": 157, "DI": 351, "GL": 11, "BH": 6, "HO": 43, "TK": 69, "RB": 38, "IF": 43, "CL": 38, "CG": 69, "FF": 33, "FA": 24, "PTS": 72}, "Richmond": {"KI": 220, "MK": 96, "HB": 162, "DI": 382, "GL": 12, "BH": 10, "HO": 30, "TK": 81, "RB": 28, "IF": 54, "CL": 35, "CG": 76, "FF": 24, "FA": 33, "PTS": 82}}, {"Collingwood": {"KI": 218, "MK": 111, "HB": 187, "DI": 405, "GL": 5, "BH": 15, "HO": 50, "TK": 84, "RB": 35, "IF": 46, "CL": 31, "CG": 55, "FF": 17, "FA": 19, "PTS": 45}, "Geelong": {"KI": 212, "MK": 86, "HB": 166, "DI": 378, "GL": 9, "BH": 12, "HO": 23, "TK": 61, "RB": 35, "IF": 46, "CL": 36, "CG": 47, "FF": 19, "FA": 17, "PTS": 66}}], "9": [{"Adelaide": {"KI": 234, "MK": 45, "HB": 96, "DI": 330, "GL": 9, "BH": 9, "HO": 57, "TK": 114, "RB": 46, "IF": 48, "CL": 53, "CG": 50, "FF": 24, "FA": 17, "PTS": 63}, "Western Bulldogs": {"KI": 212, "MK": 34, "HB": 186, "DI": 398, "GL": 2, "BH": 14, "HO": 40, "TK": 118, "RB": 35, "IF": 52, "CL": 33, "CG": 62, "FF": 17, "FA": 24, "PTS": 26}}, {"North Melbourne": {"KI": 188, "MK": 73, "HB": 164, "DI": 352, "GL": 17, "BH": 10, "HO": 45, "TK": 79, "RB": 33, "IF": 49, "CL": 45, "CG": 42, "FF": 25, "FA": 15, "PTS": 112}, "Greater Western Sydney": {"KI": 164, "MK": 54, "HB": 177, "DI": 341, "GL": 9, "BH": 15, "HO": 36, "TK": 72, "RB": 27, "IF": 50, "CL": 32, "CG": 59, "FF": 15, "FA": 25, "PTS": 69}}, {"Gold Coast": {"KI": 205, "MK": 52, "HB": 131, "DI": 336, "GL": 6, "BH": 6, "HO": 49, "TK": 83, "RB": 55, "IF": 48, "CL": 54, "CG": 80, "FF": 36, "FA": 23, "PTS": 42}, "Port Adelaide": {"KI": 231, "MK": 67, "HB": 131, "DI": 362, "GL": 11, "BH": 16, "HO": 52, "TK": 82, "RB": 41, "IF": 73, "CL": 47, "CG": 85, "FF": 23, "FA": 36, "PTS": 82}}, {"Essendon": {"KI": 249, "MK": 120, "HB": 153, "DI": 402, "GL": 12, "BH": 12, "HO": 37, "TK": 91, "RB": 42, "IF": 57, "CL": 37, "CG": 51, "FF": 24, "FA": 20, "PTS": 84}, "Geelong": {"KI": 183, "MK": 86, "HB": 167, "DI": 350, "GL": 7, "BH": 8, "HO": 33, "TK": 68, "RB": 41, "IF": 51, "CL": 31, "CG": 62, "FF": 20, "FA": 24, "PTS": 50}}, {"St Kilda": {"KI": 196, "MK": 80, "HB": 212, "DI": 408, "GL": 10, "BH": 12, "HO": 20, "TK": 50, "RB": 37, "IF": 55, "CL": 33, "CG": 67, "FF": 17, "FA": 27, "PTS": 72}, "Collingwood": {"KI": 244, "MK": 122, "HB": 209, "DI": 453, "GL": 15, "BH": 10, "HO": 44, "TK": 59, "RB": 43, "IF": 55, "CL": 36, "CG": 56, "FF": 27, "FA": 17, "PTS": 100}}, {"Sydney": {"KI": 254, "MK": 129, "HB": 173, "DI": 427, "GL": 17, "BH": 9, "HO": 14, "TK": 34, "RB": 42, "IF": 60, "CL": 24, "CG": 47, "FF": 16, "FA": 16, "PTS": 111}, "Fremantle": {"KI": 202, "MK": 94, "HB": 153, "DI": 355, "GL": 7, "BH": 10, "HO": 51, "TK": 63, "RB": 40, "IF": 50, "CL": 32, "CG": 56, "FF": 16, "FA": 16, "PTS": 52}}, {"Carlton": {"KI": 196, "MK": 75, "HB": 150, "DI": 346, "GL": 7, "BH": 8, "HO": 25, "TK": 89, "RB": 33, "IF": 33, "CL": 38, "CG": 64, "FF": 26, "FA": 20, "PTS": 50}, "Melbourne": {"KI": 222, "MK": 89, "HB": 179, "DI": 401, "GL": 25, "BH": 9, "HO": 53, "TK": 83, "RB": 25, "IF": 63, "CL": 39, "CG": 56, "FF": 20, "FA": 26, "PTS": 159}}, {"Brisbane Lions": {"KI": 218, "MK": 101, "HB": 166, "DI": 384, "GL": 20, "BH": 9, "HO": 39, "TK": 59, "RB": 39, "IF": 51, "CL": 33, "CG": 48, "FF": 15, "FA": 19, "PTS": 129}, "Hawthorn": {"KI": 203, "MK": 80, "HB": 184, "DI": 387, "GL": 11, "BH": 7, "HO": 36, "TK": 64, "RB": 24, "IF": 52, "CL": 36, "CG": 56, "FF": 19, "FA": 15, "PTS": 73}}, {"West Coast": {"KI": 228, "MK": 111, "HB": 123, "DI": 351, "GL": 20, "BH": 10, "HO": 50, "TK": 53, "RB": 40, "IF": 45, "CL": 32, "CG": 45, "FF": 21, "FA": 10, "PTS": 130}, "Richmond": {"KI": 170, "MK": 64, "HB": 126, "DI": 296, "GL": 12, "BH": 11, "HO": 23, "TK": 42, "RB": 22, "IF": 58, "CL": 36, "CG": 54, "FF": 10, "FA": 21, "PTS": 83}}], "10": [{"Collingwood": {"KI": 242, "MK": 109, "HB": 227, "DI": 469, "GL": 13, "BH": 12, "HO": 42, "TK": 58, "RB": 43, "IF": 59, "CL": 39, "CG": 57, "FF": 22, "FA": 24, "PTS": 90}, "Western Bulldogs": {"KI": 216, "MK": 111, "HB": 158, "DI": 374, "GL": 8, "BH": 7, "HO": 22, "TK": 58, "RB": 43, "IF": 52, "CL": 33, "CG": 59, "FF": 25, "FA": 22, "PTS": 55}}, {"Richmond": {"KI": 217, "MK": 100, "HB": 148, "DI": 365, "GL": 15, "BH": 15, "HO": 25, "TK": 43, "RB": 34, "IF": 63, "CL": 34, "CG": 47, "FF": 14, "FA": 19, "PTS": 105}, "St Kilda": {"KI": 239, "MK": 119, "HB": 201, "DI": 440, "GL": 12, "BH": 5, "HO": 36, "TK": 52, "RB": 44, "IF": 48, "CL": 34, "CG": 64, "FF": 19, "FA": 14, "PTS": 77}}, {"Brisbane Lions": {"KI": 198, "MK": 59, "HB": 148, "DI": 346, "GL": 6, "BH": 13, "HO": 72, "TK": 81, "RB": 37, "IF": 56, "CL": 52, "CG": 62, "FF": 30, "FA": 25, "PTS": 49}, "Sydney": {"KI": 207, "MK": 51, "HB": 176, "DI": 383, "GL": 10, "BH": 7, "HO": 22, "TK": 59, "RB": 48, "IF": 51, "CL": 40, "CG": 70, "FF": 25, "FA": 30, "PTS": 67}}, {"Geelong": {"KI": 214, "MK": 97, "HB": 132, "DI": 346, "GL": 11, "BH": 7, "HO": 36, "TK": 71, "RB": 43, "IF": 47, "CL": 38, "CG": 64, "FF": 29, "FA": 31, "PTS": 73}, "Carlton": {"KI": 210, "MK": 81, "HB": 127, "DI": 337, "GL": 5, "BH": 15, "HO": 45, "TK": 75, "RB": 34, "IF": 51, "CL": 34, "CG": 61, "FF": 31, "FA": 29, "PTS": 45}}, {"Greater Western Sydney": {"KI": 216, "MK": 83, "HB": 155, "DI": 371, "GL": 8, "BH": 12, "HO": 44, "TK": 58, "RB": 35, "IF": 56, "CL": 42, "CG": 50, "FF": 22, "FA": 15, "PTS": 60}, "Essendon": {"KI": 229, "MK": 69, "HB": 122, "DI": 351, "GL": 14, "BH": 11, "HO": 60, "TK": 85, "RB": 43, "IF": 53, "CL": 55, "CG": 58, "FF": 15, "FA": 22, "PTS": 95}}, {"Hawthorn": {"KI": 224, "MK": 99, "HB": 139, "DI": 363, "GL": 9, "BH": 6, "HO": 34, "TK": 76, "RB": 31, "IF": 48, "CL": 33, "CG": 51, "FF": 23, "FA": 19, "PTS": 60}, "West Coast": {"KI": 220, "MK": 106, "HB": 137, "DI": 357, "GL": 11, "BH": 9, "HO": 52, "TK": 63, "RB": 35, "IF": 46, "CL": 43, "CG": 61, "FF": 19, "FA": 23, "PTS": 75}}, {"Melbourne": {"KI": 245, "MK": 125, "HB": 223, "DI": 468, "GL": 23, "BH": 8, "HO": 54, "TK": 60, "RB": 28, "IF": 62, "CL": 40, "CG": 44, "FF": 22, "FA": 13, "PTS": 146}, "Adelaide": {"KI": 201, "MK": 90, "HB": 144, "DI": 345, "GL": 8, "BH": 7, "HO": 26, "TK": 66, "RB": 38, "IF": 38, "CL": 27, "CG": 49, "FF": 13, "FA": 22, "PTS": 55}}, {"Fremantle": {"KI": 209, "MK": 88, "HB": 142, "DI": 351, "GL": 8, "BH": 10, "HO": 42, "TK": 83, "RB": 41, "IF": 46, "CL": 41, "CG": 69, "FF": 21, "FA": 24, "PTS": 58}, "North Melbourne": {"KI": 202, "MK": 67, "HB": 147, "DI": 349, "GL": 12, "BH": 14, "HO": 46, "TK": 79, "RB": 32, "IF": 60, "CL": 35, "CG": 68, "FF": 24, "FA": 21, "PTS": 86}}], "11": [{"Sydney": {"KI": 196, "MK": 89, "HB": 158, "DI": 354, "GL": 13, "BH": 13, "HO": 30, "TK": 61, "RB": 32, "IF": 62, "CL": 33, "CG": 52, "FF": 22, "FA": 27, "PTS": 91}, "Carlton": {"KI": 200, "MK": 85, "HB": 111, "DI": 311, "GL": 9, "BH": 7, "HO": 43, "TK": 49, "RB": 44, "IF": 41, "CL": 38, "CG": 67, "FF": 27, "FA": 22, "PTS": 61}}, {"Western Bulldogs": {"KI": 195, "MK": 66, "HB": 191, "DI": 386, "GL": 7, "BH": 9, "HO": 26, "TK": 61, "RB": 48, "IF": 51, "CL": 48, "CG": 52, "FF": 26, "FA": 18, "PTS": 51}, "Melbourne": {"KI": 230, "MK": 119, "HB": 224, "DI": 454, "GL": 15, "BH": 10, "HO": 59, "TK": 61, "RB": 43, "IF": 68, "CL": 27, "CG": 64, "FF": 18, "FA": 26, "PTS": 100}}, {"Hawthorn": {"KI": 240, "MK": 143, "HB": 129, "DI": 369, "GL": 9, "BH": 10, "HO": 31, "TK": 53, "RB": 28, "IF": 59, "CL": 27, "CG": 56, "FF": 31, "FA": 23, "PTS": 64}, "Port Adelaide": {"KI": 206, "MK": 96, "HB": 127, "DI": 333, "GL": 9, "BH": 7, "HO": 40, "TK": 53, "RB": 48, "IF": 38, "CL": 40, "CG": 77, "FF": 23, "FA": 31, "PTS": 61}}, {"Gold Coast": {"KI": 200, "MK": 116, "HB": 97, "DI": 297, "GL": 4, "BH": 12, "HO": 52, "TK": 41, "RB": 41, "IF": 41, "CL": 29, "CG": 42, "FF": 20, "FA": 22, "PTS": 36}, "Geelong": {"KI": 230, "MK": 117, "HB": 206, "DI": 436, "GL": 17, "BH": 19, "HO": 22, "TK": 46, "RB": 34, "IF": 62, "CL": 31, "CG": 43, "FF": 22, "FA": 20, "PTS": 121}}, {"Essendon": {"KI": 217, "MK": 96, "HB": 144, "DI": 361, "GL": 6, "BH": 7, "HO": 48, "TK": 64, "RB": 39, "IF": 56, "CL": 43, "CG": 72, "FF": 22, "FA": 19, "PTS": 43}, "Richmond": {"KI": 223, "MK": 92, "HB": 143, "DI": 366, "GL": 17, "BH": 12, "HO": 18, "TK": 60, "RB": 46, "IF": 59, "CL": 29, "CG": 59, "FF": 19, "FA": 22, "PTS": 114}}, {"West Coast": {"KI": 230, "MK": 125, "HB": 126, "DI": 356, "GL": 16, "BH": 5, "HO": 38, "TK": 53, "RB": 32, "IF": 44, "CL": 33, "CG": 41, "FF": 25, "FA": 12, "PTS": 101}, "St Kilda": {"KI": 208, "MK": 98, "HB": 210, "DI": 418, "GL": 14, "BH": 4, "HO": 32, "TK": 68, "RB": 26, "IF": 48, "CL": 40, "CG": 61, "FF": 12, "FA": 25, "PTS": 88}}, {"North Melbourne": {"KI": 193, "MK": 83, "HB": 224, "DI": 417, "GL": 21, "BH": 15, "HO": 43, "TK": 50, "RB": 33, "IF": 56, "CL": 42, "CG": 49, "FF": 15, "FA": 25, "PTS": 141}, "Brisbane Lions": {"KI": 210, "MK": 100, "HB": 165, "DI": 375, "GL": 12, "BH": 15, "HO": 38, "TK": 58, "RB": 33, "IF": 51, "CL": 35, "CG": 44, "FF": 25, "FA": 15, "PTS": 87}}, {"Collingwood": {"KI": 236, "MK": 119, "HB": 196, "DI": 432, "GL": 21, "BH": 12, "HO": 62, "TK": 67, "RB": 23, "IF": 62, "CL": 42, "CG": 46, "FF": 19, "FA": 13, "PTS": 138}, "Fremantle": {"KI": 199, "MK": 113, "HB": 170, "DI": 369, "GL": 12, "BH": 5, "HO": 25, "TK": 58, "RB": 39, "IF": 35, "CL": 37, "CG": 47, "FF": 13, "FA": 19, "PTS": 77}}, {"Adelaide": {"KI": 214, "MK": 65, "HB": 163, "DI": 377, "GL": 11, "BH": 15, "HO": 49, "TK": 76, "RB": 34, "IF": 57, "CL": 52, "CG": 41, "FF": 27, "FA": 13, "PTS": 81}, "Greater Western Sydney": {"KI": 221, "MK": 70, "HB": 142, "DI": 363, "GL": 14, "BH": 13, "HO": 44, "TK": 96, "RB": 43, "IF": 53, "CL": 40, "CG": 65, "FF": 13, "FA": 27, "PTS": 97}}], "12": [{"Port Adelaide": {"KI": 232, "MK": 84, "HB": 164, "DI": 396, "GL": 10, "BH": 12, "HO": 56, "TK": 77, "RB": 40, "IF": 68, "CL": 49, "CG": 51, "FF": 19, "FA": 17, "PTS": 72}, "Richmond": {"KI": 193, "MK": 62, "HB": 136, "DI": 329, "GL": 8, "BH": 10, "HO": 34, "TK": 74, "RB": 54, "IF": 49, "CL": 35, "CG": 56, "FF": 17, "FA": 19, "PTS": 58}}, {"Geelong": {"KI": 221, "MK": 121, "HB": 197, "DI": 418, "GL": 14, "BH": 12, "HO": 22, "TK": 73, "RB": 42, "IF": 51, "CL": 27, "CG": 58, "FF": 18, "FA": 32, "PTS": 96}, "North Melbourne": {"KI": 179, "MK": 61, "HB": 161, "DI": 340, "GL": 8, "BH": 11, "HO": 40, "TK": 58, "RB": 30, "IF": 51, "CL": 36, "CG": 49, "FF": 32, "FA": 18, "PTS": 59}}, {"Greater Western Sydney": {"KI": 271, "MK": 86, "HB": 193, "DI": 464, "GL": 20, "BH": 14, "HO": 29, "TK": 85, "RB": 36, "IF": 68, "CL": 54, "CG": 65, "FF": 26, "FA": 23, "PTS": 134}, "Gold Coast": {"KI": 182, "MK": 55, "HB": 106, "DI": 288, "GL": 4, "BH": 2, "HO": 76, "TK": 89, "RB": 43, "IF": 40, "CL": 36, "CG": 61, "FF": 23, "FA": 26, "PTS": 26}}, {"St Kilda": {"KI": 206, "MK": 96, "HB": 138, "DI": 344, "GL": 7, "BH": 13, "HO": 33, "TK": 60, "RB": 28, "IF": 55, "CL": 27, "CG": 44, "FF": 20, "FA": 22, "PTS": 55}, "Sydney": {"KI": 212, "MK": 106, "HB": 188, "DI": 400, "GL": 19, "BH": 12, "HO": 35, "TK": 58, "RB": 46, "IF": 49, "CL": 39, "CG": 49, "FF": 22, "FA": 20, "PTS": 126}}, {"Brisbane Lions": {"KI": 218, "MK": 112, "HB": 159, "DI": 377, "GL": 8, "BH": 14, "HO": 43, "TK": 60, "RB": 49, "IF": 44, "CL": 33, "CG": 46, "FF": 24, "FA": 24, "PTS": 62}, "Essendon": {"KI": 211, "MK": 102, "HB": 161, "DI": 372, "GL": 12, "BH": 12, "HO": 27, "TK": 75, "RB": 34, "IF": 64, "CL": 32, "CG": 54, "FF": 24, "FA": 24, "PTS": 84}}, {"Fremantle": {"KI": 230, "MK": 106, "HB": 197, "DI": 427, "GL": 10, "BH": 11, "HO": 31, "TK": 64, "RB": 36, "IF": 50, "CL": 35, "CG": 58, "FF": 18, "FA": 19, "PTS": 71}, "Adelaide": {"KI": 205, "MK": 81, "HB": 155, "DI": 360, "GL": 9, "BH": 14, "HO": 42, "TK": 54, "RB": 35, "IF": 50, "CL": 34, "CG": 43, "FF": 19, "FA": 18, "PTS": 68}}, {"Melbourne": {"KI": 185, "MK": 83, "HB": 186, "DI": 371, "GL": 14, "BH": 7, "HO": 35, "TK": 68, "RB": 41, "IF": 42, "CL": 26, "CG": 55, "FF": 18, "FA": 21, "PTS": 91}, "Collingwood": {"KI": 222, "MK": 100, "HB": 166, "DI": 388, "GL": 20, "BH": 13, "HO": 47, "TK": 71, "RB": 26, "IF": 63, "CL": 45, "CG": 52, "FF": 21, "FA": 18, "PTS": 133}}], "13": [{"Port Adelaide": {"KI": 221, "MK": 89, "HB": 165, "DI": 386, "GL": 20, "BH": 12, "HO": 56, "TK": 72, "RB": 25, "IF": 67, "CL": 49, "CG": 55, "FF": 23, "FA": 26, "PTS": 132}, "Western Bulldogs": {"KI": 181, "MK": 67, "HB": 124, "DI": 305, "GL": 11, "BH": 9, "HO": 33, "TK": 51, "RB": 40, "IF": 40, "CL": 32, "CG": 55, "FF": 26, "FA": 23, "PTS": 75}}, {"Sydney": {"KI": 219, "MK": 92, "HB": 191, "DI": 410, "GL": 10, "BH": 12, "HO": 17, "TK": 61, "RB": 55, "IF": 52, "CL": 25, "CG": 56, "FF": 27, "FA": 27, "PTS": 72}, "West Coast": {"KI": 207, "MK": 80, "HB": 126, "DI": 333, "GL": 7, "BH": 15, "HO": 48, "TK": 57, "RB": 32, "IF": 63, "CL": 35, "CG": 59, "FF": 27, "FA": 27, "PTS": 57}}, {"Carlton": {"KI": 209, "MK": 121, "HB": 175, "DI": 384, "GL": 6, "BH": 10, "HO": 24, "TK": 55, "RB": 38, "IF": 37, "CL": 32, "CG": 53, "FF": 20, "FA": 17, "PTS": 46}, "Fremantle": {"KI": 207, "MK": 107, "HB": 154, "DI": 361, "GL": 15, "BH": 13, "HO": 49, "TK": 71, "RB": 25, "IF": 56, "CL": 32, "CG": 50, "FF": 17, "FA": 20, "PTS": 103}}, {"Gold Coast": {"KI": 191, "MK": 86, "HB": 104, "DI": 295, "GL": 11, "BH": 12, "HO": 41, "TK": 73, "RB": 44, "IF": 41, "CL": 21, "CG": 54, "FF": 21, "FA": 28, "PTS": 78}, "St Kilda": {"KI": 218, "MK": 105, "HB": 143, "DI": 361, "GL": 11, "BH": 14, "HO": 33, "TK": 75, "RB": 22, "IF": 58, "CL": 54, "CG": 44, "FF": 28, "FA": 21, "PTS": 80}}, {"Hawthorn": {"KI": 221, "MK": 89, "HB": 194, "DI": 415, "GL": 12, "BH": 16, "HO": 50, "TK": 56, "RB": 29, "IF": 61, "CL": 49, "CG": 55, "FF": 22, "FA": 21, "PTS": 88}, "Adelaide": {"KI": 220, "MK": 115, "HB": 129, "DI": 349, "GL": 4, "BH": 8, "HO": 32, "TK": 46, "RB": 42, "IF": 35, "CL": 27, "CG": 58, "FF": 21, "FA": 22, "PTS": 32}}, {"Geelong": {"KI": 190, "MK": 53, "HB": 155, "DI": 345, "GL": 9, "BH": 11, "HO": 41, "TK": 65, "RB": 34, "IF": 61, "CL": 44, "CG": 74, "FF": 28, "FA": 25, "PTS": 65}, "Richmond": {"KI": 214, "MK": 79, "HB": 133, "DI": 347, "GL": 12, "BH": 11, "HO": 35, "TK": 82, "RB": 49, "IF": 52, "CL": 34, "CG": 73, "FF": 25, "FA": 28, "PTS": 83}}], "14": [{"West Coast": {"KI": 203, "MK": 87, "HB": 116, "DI": 319, "GL": 6, "BH": 16, "HO": 49, "TK": 65, "RB": 30, "IF": 59, "CL": 32, "CG": 48, "FF": 33, "FA": 17, "PTS": 52}, "Essendon": {"KI": 241, "MK": 121, "HB": 151, "DI": 392, "GL": 12, "BH": 8, "HO": 30, "TK": 61, "RB": 48, "IF": 45, "CL": 40, "CG": 66, "FF": 17, "FA": 33, "PTS": 80}}, {"Port Adelaide": {"KI": 203, "MK": 83, "HB": 133, "DI": 336, "GL": 11, "BH": 9, "HO": 57, "TK": 99, "RB": 56, "IF": 39, "CL": 38, "CG": 45, "FF": 30, "FA": 24, "PTS": 75}, "Melbourne": {"KI": 188, "MK": 52, "HB": 169, "DI": 357, "GL": 9, "BH": 11, "HO": 54, "TK": 89, "RB": 24, "IF": 69, "CL": 54, "CG": 66, "FF": 24, "FA": 30, "PTS": 65}}, {"Hawthorn": {"KI": 224, "MK": 114, "HB": 156, "DI": 380, "GL": 13, "BH": 18, "HO": 31, "TK": 60, "RB": 31, "IF": 57, "CL": 29, "CG": 48, "FF": 20, "FA": 24, "PTS": 96}, "Gold Coast": {"KI": 184, "MK": 67, "HB": 130, "DI": 314, "GL": 5, "BH": 13, "HO": 43, "TK": 71, "RB": 40, "IF": 42, "CL": 34, "CG": 57, "FF": 24, "FA": 20, "PTS": 43}}, {"Brisbane Lions": {"KI": 235, "MK": 127, "HB": 163, "DI": 398, "GL": 12, "BH": 10, "HO": 47, "TK": 34, "RB": 38, "IF": 59, "CL": 33, "CG": 50, "FF": 28, "FA": 20, "PTS": 82}, "Greater Western Sydney": {"KI": 202, "MK": 97, "HB": 160, "DI": 362, "GL": 16, "BH": 13, "HO": 28, "TK": 47, "RB": 45, "IF": 60, "CL": 39, "CG": 56, "FF": 20, "FA": 28, "PTS": 109}}, {"Western Bulldogs": {"KI": 207, "MK": 96, "HB": 178, "DI": 385, "GL": 11, "BH": 9, "HO": 22, "TK": 53, "RB": 39, "IF": 55, "CL": 27, "CG": 55, "FF": 23, "FA": 23, "PTS": 75}, "North Melbourne": {"KI": 189, "MK": 81, "HB": 163, "DI": 352, "GL": 12, "BH": 5, "HO": 43, "TK": 53, "RB": 39, "IF": 52, "CL": 31, "CG": 62, "FF": 23, "FA": 23, "PTS": 77}}, {"Collingwood": {"KI": 219, "MK": 108, "HB": 168, "DI": 387, "GL": 11, "BH": 13, "HO": 40, "TK": 51, "RB": 27, "IF": 53, "CL": 31, "CG": 49, "FF": 30, "FA": 19, "PTS": 79}, "Carlton": {"KI": 207, "MK": 124, "HB": 129, "DI": 336, "GL": 9, "BH": 5, "HO": 14, "TK": 58, "RB": 39, "IF": 37, "CL": 27, "CG": 57, "FF": 19, "FA": 30, "PTS": 59}}], "15": [{"Richmond": {"KI": 221, "MK": 109, "HB": 153, "DI": 374, "GL": 14, "BH": 9, "HO": 45, "TK": 69, "RB": 31, "IF": 61, "CL": 31, "CG": 57, "FF": 19, "FA": 24, "PTS": 93}, "Sydney": {"KI": 176, "MK": 66, "HB": 160, "DI": 336, "GL": 11, "BH": 1, "HO": 40, "TK": 84, "RB": 46, "IF": 43, "CL": 39, "CG": 62, "FF": 24, "FA": 19, "PTS": 67}}, {"Western Bulldogs": {"KI": 201, "MK": 80, "HB": 194, "DI": 395, "GL": 16, "BH": 7, "HO": 35, "TK": 69, "RB": 34, "IF": 57, "CL": 34, "CG": 47, "FF": 18, "FA": 15, "PTS": 103}, "Geelong": {"KI": 213, "MK": 93, "HB": 195, "DI": 408, "GL": 15, "BH": 11, "HO": 40, "TK": 75, "RB": 40, "IF": 52, "CL": 39, "CG": 45, "FF": 15, "FA": 18, "PTS": 101}}, {"Carlton": {"KI": 204, "MK": 75, "HB": 176, "DI": 380, "GL": 10, "BH": 9, "HO": 44, "TK": 51, "RB": 49, "IF": 38, "CL": 35, "CG": 62, "FF": 21, "FA": 23, "PTS": 69}, "Port Adelaide": {"KI": 223, "MK": 99, "HB": 136, "DI": 359, "GL": 13, "BH": 12, "HO": 42, "TK": 75, "RB": 26, "IF": 64, "CL": 40, "CG": 48, "FF": 23, "FA": 21, "PTS": 90}}, {"Adelaide": {"KI": 215, "MK": 79, "HB": 150, "DI": 365, "GL": 12, "BH": 16, "HO": 40, "TK": 53, "RB": 20, "IF": 66, "CL": 44, "CG": 56, "FF": 18, "FA": 20, "PTS": 88}, "West Coast": {"KI": 216, "MK": 89, "HB": 119, "DI": 335, "GL": 12, "BH": 6, "HO": 47, "TK": 81, "RB": 46, "IF": 34, "CL": 34, "CG": 50, "FF": 20, "FA": 18, "PTS": 78}}, {"Gold Coast": {"KI": 229, "MK": 101, "HB": 169, "DI": 398, "GL": 8, "BH": 12, "HO": 34, "TK": 62, "RB": 35, "IF": 58, "CL": 39, "CG": 68, "FF": 14, "FA": 19, "PTS": 60}, "Collingwood": {"KI": 219, "MK": 84, "HB": 192, "DI": 411, "GL": 14, "BH": 15, "HO": 56, "TK": 69, "RB": 46, "IF": 52, "CL": 43, "CG": 48, "FF": 19, "FA": 14, "PTS": 99}}, {"Greater Western Sydney": {"KI": 212, "MK": 65, "HB": 176, "DI": 388, "GL": 13, "BH": 17, "HO": 42, "TK": 72, "RB": 31, "IF": 56, "CL": 51, "CG": 62, "FF": 26, "FA": 29, "PTS": 95}, "Hawthorn": {"KI": 196, "MK": 81, "HB": 162, "DI": 358, "GL": 13, "BH": 6, "HO": 43, "TK": 108, "RB": 35, "IF": 47, "CL": 28, "CG": 62, "FF": 30, "FA": 26, "PTS": 84}}, {"Melbourne": {"KI": 193, "MK": 83, "HB": 168, "DI": 361, "GL": 18, "BH": 9, "HO": 47, "TK": 63, "RB": 31, "IF": 62, "CL": 37, "CG": 55, "FF": 28, "FA": 23, "PTS": 117}, "St Kilda": {"KI": 207, "MK": 86, "HB": 180, "DI": 387, "GL": 18, "BH": 11, "HO": 31, "TK": 48, "RB": 42, "IF": 50, "CL": 32, "CG": 67, "FF": 23, "FA": 28, "PTS": 119}}, {"Essendon": {"KI": 214, "MK": 91, "HB": 187, "DI": 401, "GL": 19, "BH": 11, "HO": 34, "TK": 68, "RB": 34, "IF": 61, "CL": 41, "CG": 56, "FF": 11, "FA": 21, "PTS": 125}, "North Melbourne": {"KI": 212, "MK": 105, "HB": 148, "DI": 360, "GL": 16, "BH": 12, "HO": 49, "TK": 55, "RB": 37, "IF": 55, "CL": 33, "CG": 41, "FF": 21, "FA": 11, "PTS": 108}}, {"Fremantle": {"KI": 174, "MK": 79, "HB": 142, "DI": 316, "GL": 9, "BH": 10, "HO": 31, "TK": 63, "RB": 31, "IF": 47, "CL": 37, "CG": 51, "FF": 30, "FA": 18, "PTS": 64}, "Brisbane Lions": {"KI": 226, "MK": 112, "HB": 167, "DI": 393, "GL": 18, "BH": 11, "HO": 56, "TK": 54, "RB": 32, "IF": 50, "CL": 46, "CG": 62, "FF": 18, "FA": 30, "PTS": 119}}], "16": [{"Sydney": {"KI": 186, "MK": 69, "HB": 157, "DI": 343, "GL": 9, "BH": 5, "HO": 37, "TK": 73, "RB": 47, "IF": 46, "CL": 35, "CG": 51, "FF": 19, "FA": 17, "PTS": 59}, "Geelong": {"KI": 195, "MK": 68, "HB": 179, "DI": 374, "GL": 8, "BH": 23, "HO": 42, "TK": 71, "RB": 37, "IF": 59, "CL": 37, "CG": 53, "FF": 17, "FA": 19, "PTS": 71}}, {"Richmond": {"KI": 235, "MK": 93, "HB": 214, "DI": 449, "GL": 15, "BH": 13, "HO": 32, "TK": 61, "RB": 32, "IF": 67, "CL": 40, "CG": 47, "FF": 20, "FA": 17, "PTS": 103}, "Adelaide": {"KI": 221, "MK": 96, "HB": 173, "DI": 394, "GL": 8, "BH": 8, "HO": 50, "TK": 56, "RB": 47, "IF": 45, "CL": 39, "CG": 56, "FF": 17, "FA": 20, "PTS": 56}}, {"Brisbane Lions": {"KI": 252, "MK": 147, "HB": 190, "DI": 442, "GL": 18, "BH": 12, "HO": 35, "TK": 49, "RB": 42, "IF": 49, "CL": 36, "CG": 56, "FF": 24, "FA": 17, "PTS": 120}, "Carlton": {"KI": 157, "MK": 65, "HB": 140, "DI": 297, "GL": 7, "BH": 13, "HO": 34, "TK": 58, "RB": 28, "IF": 51, "CL": 30, "CG": 55, "FF": 17, "FA": 24, "PTS": 55}}, {"Port Adelaide": {"KI": 241, "MK": 113, "HB": 175, "DI": 416, "GL": 12, "BH": 14, "HO": 36, "TK": 69, "RB": 38, "IF": 67, "CL": 32, "CG": 50, "FF": 27, "FA": 17, "PTS": 86}, "St Kilda": {"KI": 185, "MK": 68, "HB": 182, "DI": 367, "GL": 7, "BH": 8, "HO": 24, "TK": 58, "RB": 48, "IF": 46, "CL": 30, "CG": 70, "FF": 17, "FA": 27, "PTS": 50}}, {"Western Bulldogs": {"KI": 203, "MK": 98, "HB": 172, "DI": 375, "GL": 9, "BH": 5, "HO": 36, "TK": 59, "RB": 33, "IF": 47, "CL": 34, "CG": 44, "FF": 18, "FA": 21, "PTS": 59}, "Hawthorn": {"KI": 224, "MK": 108, "HB": 182, "DI": 406, "GL": 19, "BH": 8, "HO": 51, "TK": 74, "RB": 35, "IF": 54, "CL": 41, "CG": 47, "FF": 21, "FA": 18, "PTS": 122}}, {"Melbourne": {"KI": 240, "MK": 89, "HB": 202, "DI": 442, "GL": 13, "BH": 24, "HO": 49, "TK": 69, "RB": 19, "IF": 78, "CL": 42, "CG": 61, "FF": 23, "FA": 21, "PTS": 102}, "Fremantle": {"KI": 188, "MK": 70, "HB": 151, "DI": 339, "GL": 7, "BH": 6, "HO": 32, "TK": 78, "RB": 55, "IF": 28, "CL": 28, "CG": 63, "FF": 21, "FA": 23, "PTS": 48}}, {"North Melbourne": {"KI": 214, "MK": 101, "HB": 226, "DI": 440, "GL": 14, "BH": 11, "HO": 38, "TK": 74, "RB": 23, "IF": 63, "CL": 37, "CG": 59, "FF": 27, "FA": 17, "PTS": 95}, "Gold Coast": {"KI": 181, "MK": 83, "HB": 169, "DI": 350, "GL": 8, "BH": 10, "HO": 45, "TK": 60, "RB": 46, "IF": 37, "CL": 38, "CG": 76, "FF": 17, "FA": 27, "PTS": 58}}, {"Essendon": {"KI": 207, "MK": 92, "HB": 176, "DI": 383, "GL": 9, "BH": 8, "HO": 36, "TK": 56, "RB": 34, "IF": 46, "CL": 35, "CG": 60, "FF": 17, "FA": 27, "PTS": 62}, "Collingwood": {"KI": 203, "MK": 88, "HB": 177, "DI": 380, "GL": 12, "BH": 6, "HO": 41, "TK": 56, "RB": 34, "IF": 47, "CL": 42, "CG": 54, "FF": 27, "FA": 17, "PTS": 78}}, {"West Coast": {"KI": 220, "MK": 106, "HB": 120, "DI": 340, "GL": 13, "BH": 8, "HO": 58, "TK": 60, "RB": 37, "IF": 49, "CL": 43, "CG": 37, "FF": 19, "FA": 17, "PTS": 86}, "Greater Western Sydney": {"KI": 190, "MK": 79, "HB": 182, "DI": 372, "GL": 10, "BH": 15, "HO": 29, "TK": 63, "RB": 36, "IF": 52, "CL": 33, "CG": 40, "FF": 17, "FA": 19, "PTS": 75}}], "17": [{"Adelaide": {"KI": 223, "MK": 92, "HB": 187, "DI": 410, "GL": 16, "BH": 16, "HO": 44, "TK": 62, "RB": 37, "IF": 56, "CL": 27, "CG": 38, "FF": 21, "FA": 18, "PTS": 112}, "Geelong": {"KI": 203, "MK": 68, "HB": 178, "DI": 381, "GL": 14, "BH": 13, "HO": 36, "TK": 68, "RB": 37, "IF": 55, "CL": 54, "CG": 64, "FF": 18, "FA": 21, "PTS": 97}}, {"St Kilda": {"KI": 223, "MK": 103, "HB": 197, "DI": 420, "GL": 16, "BH": 20, "HO": 52, "TK": 79, "RB": 25, "IF": 67, "CL": 35, "CG": 52, "FF": 27, "FA": 17, "PTS": 116}, "Carlton": {"KI": 163, "MK": 74, "HB": 194, "DI": 357, "GL": 7, "BH": 10, "HO": 24, "TK": 53, "RB": 40, "IF": 36, "CL": 31, "CG": 62, "FF": 17, "FA": 27, "PTS": 52}}, {"Hawthorn": {"KI": 216, "MK": 92, "HB": 168, "DI": 384, "GL": 9, "BH": 11, "HO": 32, "TK": 67, "RB": 29, "IF": 55, "CL": 29, "CG": 63, "FF": 20, "FA": 22, "PTS": 65}, "Brisbane Lions": {"KI": 206, "MK": 77, "HB": 183, "DI": 389, "GL": 15, "BH": 8, "HO": 40, "TK": 66, "RB": 43, "IF": 51, "CL": 44, "CG": 67, "FF": 22, "FA": 20, "PTS": 98}}, {"Melbourne": {"KI": 219, "MK": 102, "HB": 168, "DI": 387, "GL": 18, "BH": 11, "HO": 51, "TK": 63, "RB": 46, "IF": 52, "CL": 31, "CG": 69, "FF": 16, "FA": 21, "PTS": 119}, "Western Bulldogs": {"KI": 202, "MK": 70, "HB": 221, "DI": 423, "GL": 10, "BH": 9, "HO": 24, "TK": 68, "RB": 30, "IF": 57, "CL": 38, "CG": 54, "FF": 21, "FA": 16, "PTS": 69}}, {"Gold Coast": {"KI": 189, "MK": 77, "HB": 120, "DI": 309, "GL": 6, "BH": 15, "HO": 37, "TK": 61, "RB": 47, "IF": 47, "CL": 32, "CG": 56, "FF": 20, "FA": 17, "PTS": 51}, "Essendon": {"KI": 256, "MK": 121, "HB": 169, "DI": 425, "GL": 13, "BH": 17, "HO": 38, "TK": 69, "RB": 39, "IF": 66, "CL": 40, "CG": 65, "FF": 17, "FA": 20, "PTS": 95}}, {"Greater Western Sydney": {"KI": 235, "MK": 92, "HB": 149, "DI": 384, "GL": 11, "BH": 13, "HO": 40, "TK": 57, "RB": 51, "IF": 57, "CL": 42, "CG": 58, "FF": 22, "FA": 17, "PTS": 79}, "Richmond": {"KI": 210, "MK": 81, "HB": 174, "DI": 384, "GL": 10, "BH": 17, "HO": 27, "TK": 50, "RB": 41, "IF": 64, "CL": 30, "CG": 66, "FF": 17, "FA": 22, "PTS": 77}}, {"Collingwood": {"KI": 204, "MK": 94, "HB": 160, "DI": 364, "GL": 9, "BH": 13, "HO": 33, "TK": 42, "RB": 33, "IF": 53, "CL": 33, "CG": 80, "FF": 24, "FA": 28, "PTS": 67}, "West Coast": {"KI": 242, "MK": 117, "HB": 113, "DI": 355, "GL": 15, "BH": 12, "HO": 26, "TK": 63, "RB": 40, "IF": 54, "CL": 29, "CG": 53, "FF": 28, "FA": 24, "PTS": 102}}, {"North Melbourne": {"KI": 193, "MK": 90, "HB": 182, "DI": 375, "GL": 15, "BH": 8, "HO": 56, "TK": 51, "RB": 34, "IF": 51, "CL": 36, "CG": 49, "FF": 20, "FA": 9, "PTS": 98}, "Sydney": {"KI": 219, "MK": 105, "HB": 172, "DI": 391, "GL": 16, "BH": 8, "HO": 25, "TK": 52, "RB": 36, "IF": 52, "CL": 33, "CG": 59, "FF": 9, "FA": 20, "PTS": 104}}, {"Fremantle": {"KI": 223, "MK": 73, "HB": 145, "DI": 368, "GL": 8, "BH": 11, "HO": 44, "TK": 78, "RB": 30, "IF": 58, "CL": 36, "CG": 47, "FF": 23, "FA": 14, "PTS": 59}, "Port Adelaide": {"KI": 210, "MK": 71, "HB": 175, "DI": 385, "GL": 7, "BH": 8, "HO": 41, "TK": 67, "RB": 43, "IF": 39, "CL": 38, "CG": 69, "FF": 14, "FA": 23, "PTS": 50}}], "18": [{"St Kilda": {"KI": 192, "MK": 100, "HB": 193, "DI": 385, "GL": 8, "BH": 9, "HO": 38, "TK": 53, "RB": 32, "IF": 42, "CL": 37, "CG": 49, "FF": 24, "FA": 13, "PTS": 57}, "Richmond": {"KI": 196, "MK": 96, "HB": 165, "DI": 361, "GL": 16, "BH": 15, "HO": 27, "TK": 54, "RB": 30, "IF": 52, "CL": 31, "CG": 58, "FF": 13, "FA": 24, "PTS": 111}}, {"Collingwood": {"KI": 219, "MK": 104, "HB": 167, "DI": 386, "GL": 20, "BH": 10, "HO": 32, "TK": 83, "RB": 33, "IF": 57, "CL": 30, "CG": 48, "FF": 23, "FA": 17, "PTS": 130}, "North Melbourne": {"KI": 164, "MK": 71, "HB": 193, "DI": 357, "GL": 9, "BH": 10, "HO": 30, "TK": 47, "RB": 33, "IF": 44, "CL": 34, "CG": 59, "FF": 17, "FA": 23, "PTS": 64}}, {"Sydney": {"KI": 201, "MK": 80, "HB": 179, "DI": 380, "GL": 8, "BH": 16, "HO": 33, "TK": 83, "RB": 47, "IF": 48, "CL": 44, "CG": 59, "FF": 24, "FA": 25, "PTS": 64}, "Gold Coast": {"KI": 199, "MK": 78, "HB": 146, "DI": 345, "GL": 12, "BH": 16, "HO": 59, "TK": 76, "RB": 38, "IF": 61, "CL": 43, "CG": 60, "FF": 25, "FA": 24, "PTS": 88}}, {"Essendon": {"KI": 208, "MK": 86, "HB": 171, "DI": 379, "GL": 13, "BH": 21, "HO": 50, "TK": 69, "RB": 24, "IF": 62, "CL": 41, "CG": 54, "FF": 22, "FA": 24, "PTS": 99}, "Fremantle": {"KI": 172, "MK": 68, "HB": 146, "DI": 318, "GL": 11, "BH": 4, "HO": 21, "TK": 54, "RB": 43, "IF": 36, "CL": 27, "CG": 48, "FF": 24, "FA": 22, "PTS": 70}}, {"Brisbane Lions": {"KI": 211, "MK": 99, "HB": 135, "DI": 346, "GL": 13, "BH": 10, "HO": 49, "TK": 51, "RB": 46, "IF": 52, "CL": 41, "CG": 42, "FF": 16, "FA": 17, "PTS": 88}, "Adelaide": {"KI": 214, "MK": 83, "HB": 148, "DI": 362, "GL": 13, "BH": 15, "HO": 38, "TK": 50, "RB": 36, "IF": 63, "CL": 39, "CG": 49, "FF": 17, "FA": 16, "PTS": 93}}, {"Geelong": {"KI": 215, "MK": 95, "HB": 201, "DI": 416, "GL": 16, "BH": 4, "HO": 34, "TK": 65, "RB": 42, "IF": 50, "CL": 44, "CG": 56, "FF": 18, "FA": 15, "PTS": 100}, "Melbourne": {"KI": 212, "MK": 83, "HB": 188, "DI": 400, "GL": 14, "BH": 14, "HO": 44, "TK": 78, "RB": 32, "IF": 64, "CL": 35, "CG": 54, "FF": 15, "FA": 18, "PTS": 98}}, {"Carlton": {"KI": 207, "MK": 90, "HB": 190, "DI": 397, "GL": 7, "BH": 10, "HO": 39, "TK": 54, "RB": 38, "IF": 35, "CL": 34, "CG": 50, "FF": 24, "FA": 14, "PTS": 52}, "Hawthorn": {"KI": 217, "MK": 97, "HB": 203, "DI": 420, "GL": 18, "BH": 16, "HO": 44, "TK": 54, "RB": 21, "IF": 58, "CL": 35, "CG": 54, "FF": 14, "FA": 24, "PTS": 124}}, {"West Coast": {"KI": 251, "MK": 131, "HB": 163, "DI": 414, "GL": 14, "BH": 16, "HO": 39, "TK": 67, "RB": 35, "IF": 52, "CL": 34, "CG": 51, "FF": 20, "FA": 20, "PTS": 100}, "Western Bulldogs": {"KI": 168, "MK": 75, "HB": 183, "DI": 351, "GL": 6, "BH": 10, "HO": 30, "TK": 65, "RB": 35, "IF": 44, "CL": 30, "CG": 53, "FF": 20, "FA": 20, "PTS": 46}}, {"Port Adelaide": {"KI": 220, "MK": 102, "HB": 146, "DI": 366, "GL": 8, "BH": 10, "HO": 30, "TK": 72, "RB": 36, "IF": 58, "CL": 30, "CG": 60, "FF": 17, "FA": 19, "PTS": 58}, "Greater Western Sydney": {"KI": 226, "MK": 87, "HB": 144, "DI": 370, "GL": 11, "BH": 14, "HO": 57, "TK": 74, "RB": 49, "IF": 51, "CL": 52, "CG": 58, "FF": 19, "FA": 17, "PTS": 80}}], "19": [{"Essendon": {"KI": 222, "MK": 90, "HB": 156, "DI": 378, "GL": 15, "BH": 19, "HO": 38, "TK": 65, "RB": 28, "IF": 72, "CL": 34, "CG": 41, "FF": 28, "FA": 14, "PTS": 109}, "Sydney": {"KI": 197, "MK": 95, "HB": 129, "DI": 326, "GL": 10, "BH": 6, "HO": 37, "TK": 47, "RB": 54, "IF": 39, "CL": 34, "CG": 47, "FF": 14, "FA": 28, "PTS": 66}}, {"Richmond": {"KI": 193, "MK": 86, "HB": 181, "DI": 374, "GL": 16, "BH": 9, "HO": 25, "TK": 48, "RB": 33, "IF": 57, "CL": 34, "CG": 51, "FF": 16, "FA": 19, "PTS": 105}, "Collingwood": {"KI": 199, "MK": 82, "HB": 200, "DI": 399, "GL": 12, "BH": 5, "HO": 50, "TK": 72, "RB": 38, "IF": 47, "CL": 45, "CG": 64, "FF": 19, "FA": 16, "PTS": 77}}, {"Geelong": {"KI": 215, "MK": 105, "HB": 184, "DI": 399, "GL": 18, "BH": 12, "HO": 20, "TK": 49, "RB": 36, "IF": 55, "CL": 36, "CG": 40, "FF": 22, "FA": 20, "PTS": 120}, "Brisbane Lions": {"KI": 188, "MK": 89, "HB": 177, "DI": 365, "GL": 11, "BH": 12, "HO": 35, "TK": 59, "RB": 36, "IF": 51, "CL": 32, "CG": 57, "FF": 20, "FA": 22, "PTS": 78}}, {"Greater Western Sydney": {"KI": 232, "MK": 103, "HB": 165, "DI": 397, "GL": 13, "BH": 8, "HO": 36, "TK": 58, "RB": 49, "IF": 48, "CL": 34, "CG": 40, "FF": 19, "FA": 18, "PTS": 86}, "St Kilda": {"KI": 203, "MK": 82, "HB": 190, "DI": 393, "GL": 8, "BH": 13, "HO": 37, "TK": 62, "RB": 31, "IF": 60, "CL": 36, "CG": 41, "FF": 18, "FA": 19, "PTS": 61}}, {"Gold Coast": {"KI": 191, "MK": 40, "HB": 130, "DI": 321, "GL": 5, "BH": 14, "HO": 68, "TK": 91, "RB": 38, "IF": 44, "CL": 50, "CG": 61, "FF": 16, "FA": 22, "PTS": 44}, "Carlton": {"KI": 239, "MK": 86, "HB": 144, "DI": 383, "GL": 12, "BH": 7, "HO": 52, "TK": 82, "RB": 36, "IF": 52, "CL": 44, "CG": 48, "FF": 22, "FA": 16, "PTS": 79}}, {"Adelaide": {"KI": 236, "MK": 70, "HB": 135, "DI": 371, "GL": 10, "BH": 17, "HO": 44, "TK": 103, "RB": 31, "IF": 51, "CL": 40, "CG": 37, "FF": 22, "FA": 15, "PTS": 77}, "Melbourne": {"KI": 193, "MK": 56, "HB": 152, "DI": 345, "GL": 13, "BH": 12, "HO": 74, "TK": 89, "RB": 34, "IF": 50, "CL": 57, "CG": 66, "FF": 15, "FA": 22, "PTS": 90}}, {"North Melbourne": {"KI": 214, "MK": 81, "HB": 204, "DI": 418, "GL": 12, "BH": 9, "HO": 49, "TK": 73, "RB": 37, "IF": 61, "CL": 43, "CG": 53, "FF": 16, "FA": 17, "PTS": 81}, "West Coast": {"KI": 215, "MK": 86, "HB": 114, "DI": 329, "GL": 6, "BH": 5, "HO": 41, "TK": 69, "RB": 48, "IF": 47, "CL": 35, "CG": 42, "FF": 17, "FA": 16, "PTS": 41}}, {"Western Bulldogs": {"KI": 191, "MK": 40, "HB": 147, "DI": 338, "GL": 5, "BH": 4, "HO": 43, "TK": 83, "RB": 37, "IF": 49, "CL": 50, "CG": 72, "FF": 23, "FA": 27, "PTS": 34}, "Port Adelaide": {"KI": 222, "MK": 61, "HB": 122, "DI": 344, "GL": 11, "BH": 12, "HO": 47, "TK": 86, "RB": 40, "IF": 58, "CL": 42, "CG": 60, "FF": 27, "FA": 23, "PTS": 78}}, {"Fremantle": {"KI": 197, "MK": 89, "HB": 194, "DI": 391, "GL": 7, "BH": 11, "HO": 39, "TK": 47, "RB": 44, "IF": 43, "CL": 30, "CG": 53, "FF": 12, "FA": 16, "PTS": 53}, "Hawthorn": {"KI": 243, "MK": 112, "HB": 201, "DI": 444, "GL": 17, "BH": 10, "HO": 31, "TK": 66, "RB": 29, "IF": 61, "CL": 34, "CG": 47, "FF": 16, "FA": 12, "PTS": 112}}], "20": [{"Richmond": {"KI": 223, "MK": 66, "HB": 114, "DI": 337, "GL": 12, "BH": 13, "HO": 42, "TK": 92, "RB": 30, "IF": 68, "CL": 40, "CG": 60, "FF": 15, "FA": 23, "PTS": 85}, "Geelong": {"KI": 200, "MK": 58, "HB": 204, "DI": 404, "GL": 12, "BH": 10, "HO": 41, "TK": 73, "RB": 53, "IF": 46, "CL": 47, "CG": 63, "FF": 23, "FA": 15, "PTS": 82}}, {"Hawthorn": {"KI": 253, "MK": 108, "HB": 151, "DI": 404, "GL": 16, "BH": 11, "HO": 45, "TK": 51, "RB": 30, "IF": 58, "CL": 41, "CG": 46, "FF": 17, "FA": 10, "PTS": 107}, "Essendon": {"KI": 224, "MK": 105, "HB": 160, "DI": 384, "GL": 16, "BH": 7, "HO": 41, "TK": 60, "RB": 41, "IF": 49, "CL": 37, "CG": 54, "FF": 10, "FA": 17, "PTS": 103}}, {"Brisbane Lions": {"KI": 228, "MK": 114, "HB": 147, "DI": 375, "GL": 16, "BH": 8, "HO": 41, "TK": 62, "RB": 28, "IF": 61, "CL": 47, "CG": 51, "FF": 18, "FA": 20, "PTS": 104}, "North Melbourne": {"KI": 188, "MK": 70, "HB": 155, "DI": 343, "GL": 16, "BH": 11, "HO": 35, "TK": 52, "RB": 38, "IF": 48, "CL": 33, "CG": 50, "FF": 20, "FA": 18, "PTS": 107}}, {"Adelaide": {"KI": 231, "MK": 95, "HB": 159, "DI": 390, "GL": 13, "BH": 18, "HO": 34, "TK": 70, "RB": 31, "IF": 69, "CL": 44, "CG": 50, "FF": 12, "FA": 13, "PTS": 96}, "Port Adelaide": {"KI": 208, "MK": 81, "HB": 119, "DI": 327, "GL": 14, "BH": 9, "HO": 52, "TK": 52, "RB": 47, "IF": 47, "CL": 34, "CG": 51, "FF": 13, "FA": 12, "PTS": 93}}, {"Sydney": {"KI": 220, "MK": 113, "HB": 160, "DI": 380, "GL": 11, "BH": 7, "HO": 16, "TK": 77, "RB": 40, "IF": 50, "CL": 36, "CG": 67, "FF": 19, "FA": 22, "PTS": 73}, "Collingwood": {"KI": 208, "MK": 71, "HB": 166, "DI": 374, "GL": 10, "BH": 11, "HO": 63, "TK": 78, "RB": 36, "IF": 52, "CL": 35, "CG": 70, "FF": 22, "FA": 19, "PTS": 71}}, {"St Kilda": {"KI": 221, "MK": 114, "HB": 201, "DI": 422, "GL": 9, "BH": 14, "HO": 20, "TK": 56, "RB": 36, "IF": 55, "CL": 25, "CG": 55, "FF": 15, "FA": 22, "PTS": 68}, "Western Bulldogs": {"KI": 198, "MK": 106, "HB": 226, "DI": 424, "GL": 15, "BH": 13, "HO": 29, "TK": 51, "RB": 43, "IF": 54, "CL": 30, "CG": 47, "FF": 22, "FA": 15, "PTS": 103}}, {"Carlton": {"KI": 181, "MK": 75, "HB": 125, "DI": 306, "GL": 7, "BH": 4, "HO": 41, "TK": 67, "RB": 39, "IF": 43, "CL": 27, "CG": 65, "FF": 22, "FA": 23, "PTS": 46}, "Greater Western Sydney": {"KI": 242, "MK": 100, "HB": 159, "DI": 401, "GL": 23, "BH": 13, "HO": 38, "TK": 72, "RB": 34, "IF": 65, "CL": 47, "CG": 48, "FF": 23, "FA": 22, "PTS": 151}}, {"Melbourne": {"KI": 262, "MK": 130, "HB": 164, "DI": 426, "GL": 21, "BH": 17, "HO": 37, "TK": 77, "RB": 34, "IF": 69, "CL": 33, "CG": 59, "FF": 19, "FA": 15, "PTS": 143}, "Gold Coast": {"KI": 162, "MK": 68, "HB": 140, "DI": 302, "GL": 7, "BH": 5, "HO": 48, "TK": 71, "RB": 46, "IF": 41, "CL": 29, "CG": 63, "FF": 15, "FA": 19, "PTS": 47}}, {"West Coast": {"KI": 237, "MK": 110, "HB": 150, "DI": 387, "GL": 21, "BH": 16, "HO": 39, "TK": 54, "RB": 32, "IF": 59, "CL": 36, "CG": 58, "FF": 36, "FA": 25, "PTS": 142}, "Fremantle": {"KI": 167, "MK": 73, "HB": 145, "DI": 312, "GL": 13, "BH": 6, "HO": 39, "TK": 58, "RB": 36, "IF": 49, "CL": 32, "CG": 66, "FF": 25, "FA": 36, "PTS": 84}}], "21": [{"Essendon": {"KI": 235, "MK": 117, "HB": 159, "DI": 394, "GL": 18, "BH": 14, "HO": 25, "TK": 55, "RB": 33, "IF": 60, "CL": 33, "CG": 42, "FF": 25, "FA": 12, "PTS": 122}, "St Kilda": {"KI": 186, "MK": 93, "HB": 170, "DI": 356, "GL": 11, "BH": 13, "HO": 40, "TK": 46, "RB": 35, "IF": 46, "CL": 28, "CG": 53, "FF": 12, "FA": 25, "PTS": 79}}, {"Hawthorn": {"KI": 221, "MK": 88, "HB": 152, "DI": 373, "GL": 10, "BH": 11, "HO": 52, "TK": 95, "RB": 35, "IF": 53, "CL": 46, "CG": 48, "FF": 23, "FA": 23, "PTS": 71}, "Geelong": {"KI": 184, "MK": 65, "HB": 160, "DI": 344, "GL": 8, "BH": 12, "HO": 39, "TK": 75, "RB": 42, "IF": 47, "CL": 39, "CG": 59, "FF": 23, "FA": 23, "PTS": 60}}, {"Gold Coast": {"KI": 193, "MK": 86, "HB": 172, "DI": 365, "GL": 7, "BH": 9, "HO": 42, "TK": 52, "RB": 44, "IF": 44, "CL": 40, "CG": 68, "FF": 17, "FA": 18, "PTS": 51}, "Richmond": {"KI": 203, "MK": 84, "HB": 208, "DI": 411, "GL": 19, "BH": 11, "HO": 36, "TK": 51, "RB": 32, "IF": 64, "CL": 36, "CG": 66, "FF": 18, "FA": 17, "PTS": 125}}, {"Port Adelaide": {"KI": 235, "MK": 123, "HB": 157, "DI": 392, "GL": 9, "BH": 4, "HO": 19, "TK": 62, "RB": 53, "IF": 50, "CL": 31, "CG": 61, "FF": 17, "FA": 18, "PTS": 58}, "West Coast": {"KI": 230, "MK": 97, "HB": 135, "DI": 365, "GL": 9, "BH": 8, "HO": 59, "TK": 54, "RB": 38, "IF": 65, "CL": 34, "CG": 61, "FF": 18, "FA": 17, "PTS": 62}}, {"Greater Western Sydney": {"KI": 222, "MK": 81, "HB": 124, "DI": 346, "GL": 15, "BH": 16, "HO": 44, "TK": 82, "RB": 36, "IF": 50, "CL": 39, "CG": 50, "FF": 17, "FA": 20, "PTS": 106}, "Adelaide": {"KI": 204, "MK": 79, "HB": 136, "DI": 340, "GL": 13, "BH": 14, "HO": 63, "TK": 65, "RB": 30, "IF": 51, "CL": 41, "CG": 49, "FF": 20, "FA": 17, "PTS": 92}}, {"Collingwood": {"KI": 219, "MK": 87, "HB": 177, "DI": 396, "GL": 14, "BH": 20, "HO": 37, "TK": 58, "RB": 33, "IF": 59, "CL": 41, "CG": 44, "FF": 22, "FA": 14, "PTS": 104}, "Brisbane Lions": {"KI": 216, "MK": 115, "HB": 145, "DI": 361, "GL": 11, "BH": 7, "HO": 28, "TK": 48, "RB": 42, "IF": 50, "CL": 28, "CG": 54, "FF": 14, "FA": 22, "PTS": 73}}, {"North Melbourne": {"KI": 195, "MK": 96, "HB": 148, "DI": 343, "GL": 12, "BH": 13, "HO": 39, "TK": 62, "RB": 37, "IF": 51, "CL": 27, "CG": 52, "FF": 24, "FA": 17, "PTS": 85}, "Western Bulldogs": {"KI": 216, "MK": 95, "HB": 228, "DI": 444, "GL": 13, "BH": 14, "HO": 30, "TK": 39, "RB": 32, "IF": 56, "CL": 39, "CG": 59, "FF": 17, "FA": 24, "PTS": 92}}, {"Melbourne": {"KI": 193, "MK": 82, "HB": 165, "DI": 358, "GL": 10, "BH": 18, "HO": 57, "TK": 69, "RB": 28, "IF": 60, "CL": 33, "CG": 53, "FF": 18, "FA": 19, "PTS": 78}, "Sydney": {"KI": 224, "MK": 120, "HB": 147, "DI": 371, "GL": 13, "BH": 9, "HO": 19, "TK": 77, "RB": 45, "IF": 43, "CL": 33, "CG": 41, "FF": 20, "FA": 18, "PTS": 87}}, {"Fremantle": {"KI": 220, "MK": 116, "HB": 142, "DI": 362, "GL": 15, "BH": 11, "HO": 48, "TK": 56, "RB": 38, "IF": 53, "CL": 35, "CG": 48, "FF": 19, "FA": 24, "PTS": 101}, "Carlton": {"KI": 205, "MK": 76, "HB": 139, "DI": 344, "GL": 10, "BH": 12, "HO": 32, "TK": 59, "RB": 33, "IF": 52, "CL": 41, "CG": 54, "FF": 24, "FA": 19, "PTS": 72}}], "22": [{"Richmond": {"KI": 199, "MK": 89, "HB": 162, "DI": 361, "GL": 12, "BH": 9, "HO": 25, "TK": 62, "RB": 29, "IF": 58, "CL": 30, "CG": 63, "FF": 15, "FA": 27, "PTS": 81}, "Essendon": {"KI": 210, "MK": 97, "HB": 161, "DI": 371, "GL": 11, "BH": 7, "HO": 42, "TK": 56, "RB": 44, "IF": 45, "CL": 40, "CG": 54, "FF": 27, "FA": 15, "PTS": 73}}, {"Collingwood": {"KI": 204, "MK": 73, "HB": 195, "DI": 399, "GL": 17, "BH": 13, "HO": 53, "TK": 83, "RB": 26, "IF": 64, "CL": 38, "CG": 51, "FF": 19, "FA": 11, "PTS": 115}, "Port Adelaide": {"KI": 202, "MK": 93, "HB": 154, "DI": 356, "GL": 10, "BH": 4, "HO": 25, "TK": 68, "RB": 44, "IF": 39, "CL": 35, "CG": 56, "FF": 11, "FA": 19, "PTS": 64}}, {"Geelong": {"KI": 225, "MK": 89, "HB": 166, "DI": 391, "GL": 24, "BH": 14, "HO": 41, "TK": 73, "RB": 24, "IF": 73, "CL": 36, "CG": 51, "FF": 26, "FA": 20, "PTS": 158}, "Fremantle": {"KI": 170, "MK": 62, "HB": 128, "DI": 298, "GL": 3, "BH": 7, "HO": 41, "TK": 61, "RB": 47, "IF": 30, "CL": 38, "CG": 78, "FF": 20, "FA": 26, "PTS": 25}}, {"Greater Western Sydney": {"KI": 208, "MK": 82, "HB": 128, "DI": 336, "GL": 8, "BH": 12, "HO": 45, "TK": 66, "RB": 39, "IF": 49, "CL": 34, "CG": 56, "FF": 16, "FA": 24, "PTS": 60}, "Sydney": {"KI": 210, "MK": 78, "HB": 161, "DI": 371, "GL": 11, "BH": 14, "HO": 37, "TK": 76, "RB": 40, "IF": 55, "CL": 41, "CG": 58, "FF": 24, "FA": 16, "PTS": 80}}, {"St Kilda": {"KI": 209, "MK": 81, "HB": 173, "DI": 382, "GL": 11, "BH": 10, "HO": 25, "TK": 58, "RB": 27, "IF": 51, "CL": 40, "CG": 42, "FF": 17, "FA": 18, "PTS": 76}, "Hawthorn": {"KI": 197, "MK": 83, "HB": 157, "DI": 354, "GL": 12, "BH": 8, "HO": 57, "TK": 66, "RB": 36, "IF": 44, "CL": 40, "CG": 48, "FF": 18, "FA": 17, "PTS": 80}}, {"Gold Coast": {"KI": 194, "MK": 74, "HB": 153, "DI": 347, "GL": 11, "BH": 8, "HO": 39, "TK": 55, "RB": 47, "IF": 49, "CL": 39, "CG": 71, "FF": 20, "FA": 27, "PTS": 74}, "Brisbane Lions": {"KI": 225, "MK": 102, "HB": 149, "DI": 374, "GL": 10, "BH": 18, "HO": 42, "TK": 54, "RB": 34, "IF": 60, "CL": 37, "CG": 47, "FF": 27, "FA": 20, "PTS": 78}}, {"Carlton": {"KI": 204, "MK": 89, "HB": 163, "DI": 367, "GL": 7, "BH": 7, "HO": 30, "TK": 61, "RB": 34, "IF": 37, "CL": 19, "CG": 51, "FF": 24, "FA": 24, "PTS": 49}, "Western Bulldogs": {"KI": 216, "MK": 108, "HB": 172, "DI": 388, "GL": 10, "BH": 6, "HO": 34, "TK": 70, "RB": 27, "IF": 46, "CL": 44, "CG": 53, "FF": 24, "FA": 24, "PTS": 66}}, {"West Coast": {"KI": 210, "MK": 90, "HB": 150, "DI": 360, "GL": 14, "BH": 7, "HO": 37, "TK": 74, "RB": 35, "IF": 47, "CL": 29, "CG": 42, "FF": 18, "FA": 14, "PTS": 91}, "Melbourne": {"KI": 210, "MK": 88, "HB": 176, "DI": 386, "GL": 16, "BH": 12, "HO": 43, "TK": 69, "RB": 31, "IF": 55, "CL": 43, "CG": 51, "FF": 14, "FA": 18, "PTS": 108}}, {"Adelaide": {"KI": 238, "MK": 120, "HB": 226, "DI": 464, "GL": 12, "BH": 14, "HO": 30, "TK": 57, "RB": 36, "IF": 56, "CL": 37, "CG": 48, "FF": 15, "FA": 16, "PTS": 86}, "North Melbourne": {"KI": 209, "MK": 101, "HB": 163, "DI": 372, "GL": 11, "BH": 11, "HO": 38, "TK": 68, "RB": 36, "IF": 47, "CL": 30, "CG": 53, "FF": 16, "FA": 15, "PTS": 77}}], "23": [{"Port Adelaide": {"KI": 195, "MK": 77, "HB": 170, "DI": 365, "GL": 13, "BH": 11, "HO": 66, "TK": 50, "RB": 32, "IF": 54, "CL": 40, "CG": 47, "FF": 14, "FA": 19, "PTS": 89}, "Essendon": {"KI": 231, "MK": 110, "HB": 164, "DI": 395, "GL": 17, "BH": 9, "HO": 27, "TK": 83, "RB": 37, "IF": 50, "CL": 33, "CG": 42, "FF": 19, "FA": 14, "PTS": 111}}, {"Geelong": {"KI": 243, "MK": 135, "HB": 173, "DI": 416, "GL": 22, "BH": 10, "HO": 30, "TK": 74, "RB": 27, "IF": 56, "CL": 30, "CG": 47, "FF": 19, "FA": 18, "PTS": 142}, "Gold Coast": {"KI": 200, "MK": 88, "HB": 177, "DI": 377, "GL": 5, "BH": 10, "HO": 46, "TK": 60, "RB": 33, "IF": 34, "CL": 39, "CG": 61, "FF": 18, "FA": 19, "PTS": 40}}, {"Richmond": {"KI": 200, "MK": 85, "HB": 164, "DI": 364, "GL": 15, "BH": 8, "HO": 28, "TK": 48, "RB": 30, "IF": 59, "CL": 25, "CG": 60, "FF": 10, "FA": 20, "PTS": 98}, "Western Bulldogs": {"KI": 233, "MK": 131, "HB": 180, "DI": 413, "GL": 14, "BH": 11, "HO": 20, "TK": 56, "RB": 42, "IF": 47, "CL": 30, "CG": 46, "FF": 20, "FA": 10, "PTS": 95}}, {"Fremantle": {"KI": 228, "MK": 105, "HB": 175, "DI": 403, "GL": 9, "BH": 13, "HO": 38, "TK": 58, "RB": 35, "IF": 53, "CL": 36, "CG": 57, "FF": 23, "FA": 21, "PTS": 67}, "Collingwood": {"KI": 219, "MK": 75, "HB": 153, "DI": 372, "GL": 11, "BH": 10, "HO": 40, "TK": 73, "RB": 37, "IF": 50, "CL": 33, "CG": 68, "FF": 21, "FA": 23, "PTS": 76}}, {"Carlton": {"KI": 197, "MK": 77, "HB": 155, "DI": 352, "GL": 8, "BH": 13, "HO": 36, "TK": 54, "RB": 25, "IF": 61, "CL": 37, "CG": 56, "FF": 15, "FA": 18, "PTS": 61}, "Adelaide": {"KI": 231, "MK": 123, "HB": 182, "DI": 413, "GL": 26, "BH": 9, "HO": 34, "TK": 72, "RB": 49, "IF": 54, "CL": 30, "CG": 41, "FF": 18, "FA": 15, "PTS": 165}}, {"Sydney": {"KI": 207, "MK": 76, "HB": 127, "DI": 334, "GL": 10, "BH": 14, "HO": 31, "TK": 81, "RB": 33, "IF": 53, "CL": 36, "CG": 54, "FF": 30, "FA": 17, "PTS": 74}, "Hawthorn": {"KI": 205, "MK": 67, "HB": 119, "DI": 324, "GL": 12, "BH": 11, "HO": 63, "TK": 62, "RB": 32, "IF": 50, "CL": 45, "CG": 57, "FF": 17, "FA": 30, "PTS": 83}}, {"Brisbane Lions": {"KI": 227, "MK": 104, "HB": 167, "DI": 394, "GL": 11, "BH": 6, "HO": 48, "TK": 62, "RB": 39, "IF": 49, "CL": 37, "CG": 49, "FF": 18, "FA": 20, "PTS": 72}, "West Coast": {"KI": 223, "MK": 95, "HB": 137, "DI": 360, "GL": 14, "BH": 14, "HO": 39, "TK": 55, "RB": 34, "IF": 56, "CL": 43, "CG": 49, "FF": 20, "FA": 18, "PTS": 98}}, {"Melbourne": {"KI": 222, "MK": 106, "HB": 181, "DI": 403, "GL": 15, "BH": 12, "HO": 48, "TK": 60, "RB": 39, "IF": 54, "CL": 29, "CG": 38, "FF": 19, "FA": 13, "PTS": 102}, "Greater Western Sydney": {"KI": 196, "MK": 110, "HB": 159, "DI": 355, "GL": 8, "BH": 9, "HO": 18, "TK": 46, "RB": 34, "IF": 50, "CL": 32, "CG": 42, "FF": 13, "FA": 19, "PTS": 57}}, {"St Kilda": {"KI": 210, "MK": 112, "HB": 173, "DI": 383, "GL": 14, "BH": 10, "HO": 23, "TK": 50, "RB": 35, "IF": 48, "CL": 33, "CG": 48, "FF": 14, "FA": 18, "PTS": 94}, "North Melbourne": {"KI": 224, "MK": 106, "HB": 201, "DI": 425, "GL": 17, "BH": 15, "HO": 32, "TK": 48, "RB": 29, "IF": 59, "CL": 24, "CG": 50, "FF": 18, "FA": 14, "PTS": 117}}]}